[
    {
        "title": "秋霁望庐山瀑布",
        "author": "夏侯楚",
        "content": "常思瀑布幽，晴晀喜逢秋。\n一带连青嶂，千寻倒碧流。\n湿云应悞鹤，飜浪定惊鸥。\n星浦虹初下，炉峰烟未收。\n岩高时褭褭，天净起悠悠。\n傥见朝宗日，还须济巨舟。",
        "dynasty": "唐",
        "collection_info": null
    },
    {
        "title": "秋霁望庐山瀑布",
        "author": "夏侯楚",
        "content": "常思瀑布幽，晴晀喜逢秋。一带连青嶂，千寻倒碧流。\n湿云应误鹤，翻浪定惊鸥。星浦虹初下，炉峰烟未收。\n岩高时褭褭，天净起悠悠。傥见朝宗日，还须济巨舟。",
        "dynasty": "唐",
        "collection_info": {
            "collection": "御定全唐诗",
            "volume": "卷七百八十"
        }
    }
]