[
    {
        "title": "题浯溪石",
        "author": "皇甫湜",
        "content": "次山有文章，可惋只在碎。\n然长于指叙，约洁有余态。\n心语适相应，出句多分外。\n于诸作者间，拔戟成一队。\n中行虽富剧，粹美若可盖。\n子昂感遇佳，未若君雅裁。\n退之全而神，上与千载对。\n李杜才海翻，高下非可概。\n文与一气间，为物莫与大。\n先王路不荒，岂不仰吾辈。\n石屏立衙衙，溪口扬素濑。\n我思何人知，徙倚如有待。",
        "dynasty": "唐",
        "collection_info": null
    },
    {
        "title": "石佛谷",
        "author": "皇甫湜",
        "content": "[澶漫]太行北，千里一块石。\n平腹有壑谷，深广数百尺。\n土僧何为者，老草毛髮白。\n寝处容身龛，足膝隐成迹。\n金僊琢灵象，相好倚北壁。\n花座五云扶，玉豪六虚射。\n文人留纪述，时事可辨析。\n鸟迹巧均分，龙骸极癯瘠。\n枯松间槎枿，猛兽恣腾掷。\n蛣𧎜虫食纵，悬垂露凝滴。\n精艺贯古今，穷岩谁爱惜。\n託师禅诵余，勿使尘埃积。",
        "dynasty": "唐",
        "collection_info": null
    },
    {
        "title": "出世篇",
        "author": "皇甫湜",
        "content": "生当为大丈夫，断羁罗，出泥涂。\n四散号呶，[俶扰]无隅。\n埋之深渊，飘然上浮。\n骑龙披青云，泛览游八区。\n经太山，绝大海，一长吁。\n西摩月镜，东弄日珠。\n上括天之门，直指帝所居。\n羣仙来迎塞天衢，凤皇鸾鸟灿金舆。\n音声嘈嘈满太虚，旨饮食兮照庖厨。\n食之不饫饫不尽，使人不陋復不愚。\n旦旦狎玉皇，夜夜御天姝。\n当御者几人，百千为番。\n宛宛舒舒，忽不自知。\n支消体化膏露明，湛然无色茵席濡。\n俄而散漫，[斐]然虚无。\n翕然復抟，抟久而苏。\n精神如太阳，霍然照清都。\n四肢为琅玕，五臟为璠玙。\n颜如芙蓉，顶为醍醐。\n与天地相终始，浩漫为欢娱。\n下顾人间，溷粪蝇蛆。",
        "dynasty": "唐",
        "collection_info": null
    },
    {
        "title": "题浯溪石",
        "author": "皇甫湜",
        "content": "次山有文章，可惋只在碎。然长于指叙，约洁有余态。\n心语适相应，出句多分外。于诸作者间，拔戟成一队。\n中行虽富剧，粹美若可盖。子昂感遇佳，未若君雅裁。\n退之全而神，上与千载对。李杜才海翻，高下非可概。\n文与一气间，为物莫与大。先王路不荒，岂不仰吾辈。\n石屏立衙衙，溪口扬素濑。我思何人知，徙倚如有待。",
        "dynasty": "唐",
        "collection_info": {
            "collection": "御定全唐诗",
            "volume": "卷三百六十九"
        }
    },
    {
        "title": "石佛谷",
        "author": "皇甫湜",
        "content": "澶漫太行北，千里一块石。平腹有壑谷，深广数百尺。\n土僧何为者，老草毛髮白。寝处容身龛，足膝隐成迹。\n金仙琢灵象，相好倚北壁。花座五云扶，玉毫六虚射。\n文人留纪述，时事可辨析。鸟迹巧均分，龙骸极癯瘠。\n枯松间槎枿，猛兽恣腾掷。蛣虫食纵，悬垂露凝滴。\n精艺贯古今，穷岩谁爱惜。托师禅诵余，勿使尘埃积。",
        "dynasty": "唐",
        "collection_info": {
            "collection": "御定全唐诗",
            "volume": "卷三百六十九"
        }
    },
    {
        "title": "出世篇",
        "author": "皇甫湜",
        "content": "生当为大丈夫，断羁罗，出泥涂。四散号呶，俶扰无隅。\n埋之深渊，飘然上浮。骑龙披青云，泛览游八区。\n经太山，绝大海，一长吁。西摩月镜，东弄日珠。\n上括天之门，直指帝所居。群仙来迎塞天衢，\n食之不饫饫不尽，使人不陋复不愚。旦旦狎玉皇，\n俄而散漫，斐然虚无。翕然复抟，抟久而苏。\n精神如太阳，霍然照清都。四肢为琅玕，五臟为璠玙。\n颜如芙蓉，顶为醍醐。与天地相终始，浩漫为欢娱。\n下顾人间，溷粪蝇蛆。",
        "dynasty": "唐",
        "collection_info": {
            "collection": "御定全唐诗",
            "volume": "卷三百六十九"
        }
    }
]