[
    {
        "uuid": "3c8a5e8ec31254cbba1985c62f5abadd",
        "title": "彭泽",
        "author": "汪遵",
        "content": "鹤爱孤松云爱山，宦情微禄免相关。\n栽成五柳吟归去，漉酒巾边伴菊闲。",
        "dynasty": "唐",
        "collection_info": null
    },
    {
        "uuid": "9bed65263b044a6269e61e19f9b31cf9",
        "title": "杜邮馆",
        "author": "汪遵",
        "content": "杀尽降兵热血流，一心犹自逞戈矛。\n功成若解求身退，岂得将军死杜邮。",
        "dynasty": "唐",
        "collection_info": null
    },
    {
        "uuid": "eeed535e33b593c278162296be59c862",
        "title": "细腰宫",
        "author": "汪遵",
        "content": "鼓声连日烛连宵，贪向春风舞细腰。\n争奈君王正沈醉，秦兵江上促征桡。",
        "dynasty": "唐",
        "collection_info": null
    },
    {
        "uuid": "d1d6b95905cd08da878ebca77aaabcca",
        "title": "瑶台",
        "author": "汪遵",
        "content": "仙梦香魂不久留，满川云雨满宫愁。\n直须待得荆王死，始向瑶台一处游。",
        "dynasty": "唐",
        "collection_info": null
    },
    {
        "uuid": "c1bbd7a798d9141c910e994ab1ce7af3",
        "title": "吴坂",
        "author": "汪遵",
        "content": "蜷跼盐车万里蹄，忽逢良鉴始能嘶。\n不缘伯乐称奇骨，几与驽骀价一齐。",
        "dynasty": "唐",
        "collection_info": null
    },
    {
        "uuid": "99e8ad304df6fc8dd5c1f65d41e6c1eb",
        "title": "箕山",
        "author": "汪遵",
        "content": "薄世临流洗耳尘，便归云洞任天真。\n一瓢风入犹嫌闹，何况人间万种人。",
        "dynasty": "唐",
        "collection_info": null
    },
    {
        "uuid": "4b724f87aafeafdc6259a0e74d450999",
        "title": "息国",
        "author": "汪遵",
        "content": "家国兴亡身独存，玉容还受楚王恩。\n衔冤只合甘先死，何待花间不肯言。",
        "dynasty": "唐",
        "collection_info": null
    },
    {
        "uuid": "8271f870c6215c3a5eb2fb62d9800b41",
        "title": "梁寺",
        "author": "汪遵",
        "content": "立国从来为战功，一朝何事却谈空。\n台城兵匝无人敌，闲卧高僧满梵宫。",
        "dynasty": "唐",
        "collection_info": null
    },
    {
        "uuid": "83546b77b24faca10a82bbd3c1ad9c56",
        "title": "南阳",
        "author": "汪遵",
        "content": "陆困泥蟠未适从，岂妨耕嫁隐高踪。\n若非先主垂三顾，谁识茅庐一卧龙。",
        "dynasty": "唐",
        "collection_info": null
    },
    {
        "uuid": "b7549921f44e96d328f4545ccd6d7bcc",
        "title": "杞梁墓",
        "author": "汪遵",
        "content": "一呌长城万仞摧，杞梁遗骨逐妻回。\n南邻北里皆孀妇，谁解坚心继此来。",
        "dynasty": "唐",
        "collection_info": null
    },
    {
        "uuid": "642f3fd926d3544d96212697f9aa74aa",
        "title": "夷门",
        "author": "汪遵",
        "content": "晋鄙兵回为重难，秦师收斾亦西还。\n今来不是无朱亥，谁降轩车问抱关。",
        "dynasty": "唐",
        "collection_info": null
    },
    {
        "uuid": "afa0189ff674947d724547b862754f30",
        "title": "汴河",
        "author": "汪遵",
        "content": "隋皇意欲泛龙舟，千里昆崙水别流。\n还待春风锦帆暖，柳阴相送到迷楼。",
        "dynasty": "唐",
        "collection_info": null
    },
    {
        "uuid": "b47ba050f618d6c1f7eb7f10669379e4",
        "title": "燕台",
        "author": "汪遵",
        "content": "礼士招贤万古名，高台依旧对燕城。\n如今寂寞无人上，春去秋来草自生。",
        "dynasty": "唐",
        "collection_info": null
    },
    {
        "uuid": "b6cb058221edf2f5207b0dabf62a7495",
        "title": "聊城",
        "author": "汪遵",
        "content": "刃血攻聊已越年，竟凭儒术罢戈鋋。\n田单漫逞烧牛计，一箭终输鲁仲连。",
        "dynasty": "唐",
        "collection_info": null
    },
    {
        "uuid": "1337ca247becaea2e90732614f6ffa37",
        "title": "西河",
        "author": "汪遵",
        "content": "花貌年年溺水滨，俗传河伯娶生人。\n自从明宰投巫后，直至如今鬼不神。",
        "dynasty": "唐",
        "collection_info": null
    },
    {
        "uuid": "5731a057af9e446eaf31f827758e715b",
        "title": "密县",
        "author": "汪遵",
        "content": "百里能将济猛宽，飞蝗不到邑人安。\n至今闾里逢灾沴，犹祝当时卓长官。",
        "dynasty": "唐",
        "collection_info": null
    },
    {
        "uuid": "5fc5d7fd8240e82aee5269184079f61d",
        "title": "昇仙桥",
        "author": "汪遵",
        "content": "题桥贵欲露先诚，此日人皆笑率情。\n应讶临邛沽酒客，逢时还作汉公卿。",
        "dynasty": "唐",
        "collection_info": null
    },
    {
        "uuid": "66f20986042618f7e5b50f26c10d133e",
        "title": "破陈",
        "author": "汪遵",
        "content": "猎猎朱旗映綵霞，纷纷白刃入陈家。\n看看打破东平苑，犹舞庭前玉树花。",
        "dynasty": "唐",
        "collection_info": null
    },
    {
        "uuid": "b462f8d8f4ceb119689fedb4010d8af3",
        "title": "白头吟",
        "author": "汪遵",
        "content": "失却青丝素髪生，合欢罗带意全轻。\n古今人事皆如此，不独文君与马卿。",
        "dynasty": "唐",
        "collection_info": null
    },
    {
        "uuid": "8dba546e9f1b60c92e6f462ffd91f14f",
        "title": "短歌吟",
        "author": "汪遵",
        "content": "箭飞乌兔竞东西，贵贱贤愚不梦齐。\n匣裏有琴樽有酒，人间便是武陵溪。",
        "dynasty": "唐",
        "collection_info": null
    },
    {
        "uuid": "8ff200a589ee8bde27d023d22952d715",
        "title": "晋河",
        "author": "汪遵",
        "content": "风引征帆管吹高，晋君张[宴]俟雄豪。\n舟人笑指千余客，谁是烟霄六翮毛。",
        "dynasty": "唐",
        "collection_info": null
    },
    {
        "uuid": "22554b1ca0a2ac8f13d085e9ffc7c82b",
        "title": "干将墓",
        "author": "汪遵",
        "content": "橐籥冰霜万古闻，拍灰松地见余坟。\n应缘神劒飞扬久，水水山山尽是云。",
        "dynasty": "唐",
        "collection_info": null
    },
    {
        "uuid": "35038e56871c61cf0994e9532203880a",
        "title": "金谷",
        "author": "汪遵",
        "content": "晋臣荣盛更谁过，常向阶前舞翠娥。\n香散艳消如一梦，但留风月伴烟萝。",
        "dynasty": "唐",
        "collection_info": null
    },
    {
        "uuid": "0e9df77b83c0474d8880a1d02fc083c9",
        "title": "三闾庙",
        "author": "汪遵",
        "content": "为嫌朝野尽陶陶，不觉官高怨亦高。\n憔悴莫酬渔父笑，浪交千载咏离骚。",
        "dynasty": "唐",
        "collection_info": null
    },
    {
        "uuid": "40a4e39a1b04f5280e12ff527af896b0",
        "title": "易水",
        "author": "汪遵",
        "content": "[匕]首空磨事不成，误留龙袂待琴声。\n斯须却作秦中鬼，青史徒标烈士名。",
        "dynasty": "唐",
        "collection_info": null
    },
    {
        "uuid": "7a98125cb1259b6752d9be8d1220bc25",
        "title": "严陵台",
        "author": "汪遵",
        "content": "一钓凄凉在杳冥，故人飞诏入山扃。\n终将宠辱轻轩冕，高卧五云为客星。",
        "dynasty": "唐",
        "collection_info": null
    },
    {
        "uuid": "32b27ac7c0eed8d2e23d4f0c095a9a4e",
        "title": "淮阴",
        "author": "汪遵",
        "content": "秦季贤愚混不分，只应漂母识王孙。\n归荣便累千金赠，为报当时一饭恩。",
        "dynasty": "唐",
        "collection_info": null
    },
    {
        "uuid": "2fcd6f107a46d77d1fc9769734c0dc56",
        "title": "鸡鸣曲",
        "author": "汪遵",
        "content": "金距花冠傍舍栖，清晨相呌一声齐。\n开关自有冯生计，不必天明待汝啼。",
        "dynasty": "唐",
        "collection_info": null
    },
    {
        "uuid": "5543ba81a5ec41112b3e5dd4bd2a471d",
        "title": "采桑妇",
        "author": "汪遵",
        "content": "为报踌躇陌上郎，蚕饥日晚妾心忙。\n本来若爱黄金好，不肯携笼更采桑。",
        "dynasty": "唐",
        "collection_info": null
    },
    {
        "uuid": "3fbca83f5e38a795291fc23afe295882",
        "title": "渔父",
        "author": "汪遵",
        "content": "棹月眠流处处通，绿蓑苇带混元风。\n灵均说尽孤高事，全与逍遥意不同。",
        "dynasty": "唐",
        "collection_info": null
    },
    {
        "uuid": "93530ad7218b8e6df02c41f964157eec",
        "title": "越女",
        "author": "汪遵",
        "content": "玉貌何曾为浣沙，只图句践献夫差。\n苏台日夜唯歌舞，不觉干戈犯翠华。",
        "dynasty": "唐",
        "collection_info": null
    },
    {
        "uuid": "afa4ae96d1cd0cc465d1c639f502f8d0",
        "title": "望思台",
        "author": "汪遵",
        "content": "不忧家国任姦臣，骨肉翻为蓦路人。\n巫蛊事行冤莫雪，九层徒筑见无因。",
        "dynasty": "唐",
        "collection_info": null
    },
    {
        "uuid": "a5f7ab53372fe8bdf87379eaa09b9ec4",
        "title": "比干墓",
        "author": "汪遵",
        "content": "国乱时危道不行，忠贤谏死胜谋生。\n一沈冤骨千年后，壠水虽平恨未平。",
        "dynasty": "唐",
        "collection_info": null
    },
    {
        "uuid": "00d498940f8b581b89486126aac31d41",
        "title": "郢中",
        "author": "汪遵",
        "content": "莫言白雪少人听，高调都难称俗情。\n不是楚词询宋玉，巴歌犹掩绕梁声。",
        "dynasty": "唐",
        "collection_info": null
    },
    {
        "uuid": "faeeb283173d805cad10089767ce760d",
        "title": "北海",
        "author": "汪遵",
        "content": "汉臣曾此作缧囚，茹血衣毛十九秋。\n鹤髪半垂龙节在，不闻青史说封侯。",
        "dynasty": "唐",
        "collection_info": null
    },
    {
        "uuid": "6972b692f7698a4f71aa3a14df36b822",
        "title": "招屈亭",
        "author": "汪遵",
        "content": "三闾溺处杀怀王，感得荆人尽缟裳。\n招屈亭边两重恨，远天秋色暮苍苍。",
        "dynasty": "唐",
        "collection_info": null
    },
    {
        "uuid": "a4d919c3596459021d0c27c24f7960ff",
        "title": "屈祠",
        "author": "汪遵",
        "content": "不肯迂回入醉乡，乍吞忠梗没沧浪。\n至今祠畔猨啼月，了了犹疑恨楚王。",
        "dynasty": "唐",
        "collection_info": null
    },
    {
        "uuid": "6056b4a75568ccef0801f19ea9b8f1e1",
        "title": "铜雀台",
        "author": "汪遵",
        "content": "铜雀台成玉座空，短歌长袖尽悲风。\n不知仙驾归何处，徒遣颦眉望汉宫。",
        "dynasty": "唐",
        "collection_info": null
    },
    {
        "uuid": "a70e2a6b35b1b99cf57d5833fb321273",
        "title": "斑竹祠",
        "author": "汪遵",
        "content": "九处烟霞九处昏，一回延首一销魂。\n因凭直节流红泪，图得千秋见血痕。",
        "dynasty": "唐",
        "collection_info": null
    },
    {
        "uuid": "08d91b767c66bc529ad36ea5b0bbd464",
        "title": "题李太尉平泉庄",
        "author": "汪遵",
        "content": "水泉花木好高眠，嵩少纵横满目前。\n惆怅人间不平事，今朝身在海南边。",
        "dynasty": "唐",
        "collection_info": null
    },
    {
        "uuid": "69add4d7834db75a309c6036d0b50804",
        "title": "战城南",
        "author": "汪遵",
        "content": "风沙刮地塞云愁，平旦交锋晚未休。\n白骨又霑新战血，青天犹列旧旄头。",
        "dynasty": "唐",
        "collection_info": null
    },
    {
        "uuid": "7b376cc833b844df7bcf07d2372e4e5b",
        "title": "延平津",
        "author": "汪遵",
        "content": "三尺晶荧射斗牛，岂随凡手报冤雠。\n延平一旦为龙处，看取风云布九州。",
        "dynasty": "唐",
        "collection_info": null
    },
    {
        "uuid": "ad01d29c0a74ed92954b9d09784a75c5",
        "title": "项亭",
        "author": "汪遵",
        "content": "不修仁德合文明，天道如何拟力争。\n隔岸故乡归不得，十年空负拔山名。",
        "dynasty": "唐",
        "collection_info": null
    },
    {
        "uuid": "ecdef31de2ce63373149b341dbf8c301",
        "title": "乌江",
        "author": "汪遵",
        "content": "兵散弓残挫虎威，单枪匹马突重围。\n英雄去尽羞容在，看却江东不得归。",
        "dynasty": "唐",
        "collection_info": null
    },
    {
        "uuid": "ba4619568201dd4c3eb823d92860caa4",
        "title": "绿珠",
        "author": "汪遵",
        "content": "大抵花颜最怕秋，南家歌歇北家愁。\n从来几许如君貌，不肯如君坠玉楼。",
        "dynasty": "唐",
        "collection_info": null
    },
    {
        "uuid": "340b73be000a012a1aaa629278cfd80b",
        "title": "升仙桥",
        "author": "汪遵",
        "content": "汉朝卿相尽风云，司马题桥众又闻。\n何事不如杨得意，解搜贤哲荐明君。",
        "dynasty": "唐",
        "collection_info": null
    },
    {
        "uuid": "94069a74a00e9f63f8caa90462fbe708",
        "title": "隋柳",
        "author": "汪遵",
        "content": "夹浪分堤万树余，为迎龙舸到江都。\n君看靖节高眠处，只向衡门种五株。",
        "dynasty": "唐",
        "collection_info": null
    },
    {
        "uuid": "ff1949ed0dcabb65c0f9a748bb69aebb",
        "title": "杨柳",
        "author": "汪遵",
        "content": "亚夫营畔柳蒙蒙，隋主堤边四路通。\n攀折赠君还有意，翠眉轻嫩怕春风。",
        "dynasty": "唐",
        "collection_info": null
    },
    {
        "uuid": "b4c201dedd5b844abe2b29b09f3f0b3f",
        "title": "桐江",
        "author": "汪遵",
        "content": "光武重兴四海宁，汉臣无不受浮荣。\n严陵何事轻轩冕，独向桐江钓月明。",
        "dynasty": "唐",
        "collection_info": null
    },
    {
        "uuid": "851d14e8c2a4bc7277068f39c3bd48c7",
        "title": "招隐",
        "author": "汪遵",
        "content": "罢听泉声看鹿羣，丈夫才策合匡君。\n早携书劒离岩谷，莫待蒲轮辗白云。",
        "dynasty": "唐",
        "collection_info": null
    },
    {
        "uuid": "05ab9246ffb5cbc32e540ec6934661b4",
        "title": "陈宫",
        "author": "汪遵",
        "content": "椒宫荒宴竟无疑，倏忽山河尽入隋。\n留得后庭亡国曲，至今犹与酒家吹。",
        "dynasty": "唐",
        "collection_info": null
    },
    {
        "uuid": "c7763f4bf6cf60feab13cf00261b7e4f",
        "title": "樊将军庙",
        "author": "汪遵",
        "content": "玉辇曾经陷楚营，汉皇心怯拟休兵。\n当时不得将军力，日月须分一半明。",
        "dynasty": "唐",
        "collection_info": null
    },
    {
        "uuid": "a8b413dd4d5fce4ea4aa504256735382",
        "title": "东海",
        "author": "汪遵",
        "content": "漾舟雪浪映花颜，徐福携将竟不还。\n同作危时避秦客，此行何似武陵滩。",
        "dynasty": "唐",
        "collection_info": null
    },
    {
        "uuid": "c86190db2ffb1acf1de2f9b854903f63",
        "title": "昭君",
        "author": "汪遵",
        "content": "汉家天子镇寰瀛，塞北羌胡未罢兵。\n猛将谋臣徒自贵，蛾眉一笑塞尘清。",
        "dynasty": "唐",
        "collection_info": null
    },
    {
        "uuid": "e1221e4a78e002476ce4b4abcc646a38",
        "title": "五湖",
        "author": "汪遵",
        "content": "已立平吴霸越功，片帆高扬五湖风。\n不知战国官荣者，谁似陶朱得始终。",
        "dynasty": "唐",
        "collection_info": null
    },
    {
        "uuid": "e349e650c5f893dcc5914a60bf2706e4",
        "title": "渑池",
        "author": "汪遵",
        "content": "西秦北赵各称高，池上张筵列我曹。\n何事君王亲击缶，相如有劒可吹毛。",
        "dynasty": "唐",
        "collection_info": null
    },
    {
        "uuid": "91e26134bbab76d7af1318dc50d27465",
        "title": "函谷关",
        "author": "汪遵",
        "content": "脱祸东奔壮气摧，马如飞电毂如雷。\n当时若不听弹铗，那得关门半夜开。",
        "dynasty": "唐",
        "collection_info": null
    },
    {
        "uuid": "618d2a9c49f8ef0dea49241c6f9638a2",
        "title": "咏酒二首 一",
        "author": "汪遵",
        "content": "九酝松醪一曲歌，本图闲放养天和。\n后人不识前贤意，破国亡家事甚多。",
        "dynasty": "唐",
        "collection_info": null
    },
    {
        "uuid": "777027321d6510a61c208baace1f208b",
        "title": "咏酒二首 二",
        "author": "汪遵",
        "content": "万事销沈向一杯，竹门哑轧为风开。\n秋宵睡足芭蕉雨，又是江湖入梦来。",
        "dynasty": "唐",
        "collection_info": null
    },
    {
        "uuid": "c8f4cea8d5397ad97c8ee191fa7dfa96",
        "title": "苍颉台",
        "author": "汪遵",
        "content": "观迹成文代结绳，皇风儒教浩然兴。\n几人从此休耕钓，吟对长安雪夜灯。",
        "dynasty": "唐",
        "collection_info": null
    },
    {
        "uuid": "f7795dda83cd9fdf3bb47040082dcd38",
        "title": "长城",
        "author": "汪遵",
        "content": "秦筑长城比铁牢，蕃戎不敢过临洮。\n虽然万里连云际，争及尧阶三尺高。",
        "dynasty": "唐",
        "collection_info": null
    },
    {
        "uuid": "6ed1aeb7b9e0b13228431eb154bf114e",
        "title": "过平泉庄（李朱厓〖德裕〗平泉庄，佳景可爱。洛中士人诧于「汪」〖江〗遵，遵有诗曰：）",
        "author": "汪遵",
        "content": "平泉风景好高眠，水色风光满目前。\n刚欲平他不平事，至今惆怅满南迁。\n（今按：此一首与《唐诗纪事》及《全唐诗》字句多不同。\n）。",
        "dynasty": "唐",
        "collection_info": null
    },
    {
        "uuid": "ac4fbc806e8b7f7b79e4ab079ec0c2df",
        "title": "又过杨相宅",
        "author": "汪遵",
        "content": "倚伏从来事不遥，无何平地起青霄。\n纔到青霄却平地，门对古槐空寂寥。\n（以上《诗话总龟》二四《感事门》引《唐贤抒情》）（〖1〗《万首唐人绝句》卷六九以此诗为尹璞作，文字稍异。\n《全唐诗》卷五一七收尹璞名下，幷注出《抒情录》作江遵诗之异文。\n）。",
        "dynasty": "唐",
        "collection_info": null
    },
    {
        "uuid": "4f8439342bac3beff98e2737f34319b8",
        "title": "吴阪",
        "author": "汪遵",
        "content": "蜷局盐车万里蹄，忽逢良鉴始能嘶。\n不缘伯乐称奇骨，几与驽骀价一齐。",
        "dynasty": "唐",
        "collection_info": {
            "collection": "御定全唐诗",
            "volume": "卷六百零二"
        }
    },
    {
        "uuid": "4bee1d970250af64b41bf2c0e2694c64",
        "title": "南阳",
        "author": "汪遵",
        "content": "陆困泥蟠未适从，岂妨耕稼隐高踪。\n若非先主垂三顾，谁识茅庐一卧龙。",
        "dynasty": "唐",
        "collection_info": {
            "collection": "御定全唐诗",
            "volume": "卷六百零二"
        }
    },
    {
        "uuid": "0d6f7ed19d4f22c5ae972cf63315e2d3",
        "title": "杞梁墓",
        "author": "汪遵",
        "content": "一叫长城万仞摧，杞梁遗骨逐妻回。\n南邻北裏皆孀妇，谁解坚心继此来。",
        "dynasty": "唐",
        "collection_info": {
            "collection": "御定全唐诗",
            "volume": "卷六百零二"
        }
    },
    {
        "uuid": "fa23c6f0516d0394147ff0607c5b05ef",
        "title": "夷门",
        "author": "汪遵",
        "content": "晋鄙兵回为重难，秦师收旆亦西还。\n今来不是无朱亥，谁降轩车问抱关。",
        "dynasty": "唐",
        "collection_info": {
            "collection": "御定全唐诗",
            "volume": "卷六百零二"
        }
    },
    {
        "uuid": "8aa8cbc1131f4d6fed6525b2cdbed7cb",
        "title": "汴河",
        "author": "汪遵",
        "content": "隋皇意欲泛龙舟，千里昆仑水别流。\n还待春风锦帆暖，柳阴相送到迷楼。",
        "dynasty": "唐",
        "collection_info": {
            "collection": "御定全唐诗",
            "volume": "卷六百零二"
        }
    },
    {
        "uuid": "79cdc804a8b0762feb83dc4d77a732d6",
        "title": "密县",
        "author": "汪遵",
        "content": "百里能将济猛宽，飞蝗不到邑人安。\n至今闾裏逢灾沴，犹祝当时卓长官。",
        "dynasty": "唐",
        "collection_info": {
            "collection": "御定全唐诗",
            "volume": "卷六百零二"
        }
    },
    {
        "uuid": "49a92949fe13f23933c390e27b2a3070",
        "title": "升仙桥",
        "author": "汪遵",
        "content": "题桥贵欲露先诚，此日人皆笑率情。\n应讶临邛沽酒客，逢时还作汉公卿。",
        "dynasty": "唐",
        "collection_info": {
            "collection": "御定全唐诗",
            "volume": "卷六百零二"
        }
    },
    {
        "uuid": "053e72a8427f7581f7cf38f8e633844e",
        "title": "破陈",
        "author": "汪遵",
        "content": "猎猎朱旗映彩霞，纷纷白刃入陈家。\n看看打破东平苑，犹舞庭前玉树花。",
        "dynasty": "唐",
        "collection_info": {
            "collection": "御定全唐诗",
            "volume": "卷六百零二"
        }
    },
    {
        "uuid": "aaccc76f3d113d483160311971cc6026",
        "title": "白头吟",
        "author": "汪遵",
        "content": "失却青丝素发生，合欢罗带意全轻。\n古今人事皆如此，不独文君与马卿。",
        "dynasty": "唐",
        "collection_info": {
            "collection": "御定全唐诗",
            "volume": "卷六百零二"
        }
    },
    {
        "uuid": "79bd0cfe35567bc22b6f4bd64295d7e2",
        "title": "晋河",
        "author": "汪遵",
        "content": "风引征帆管吹高，晋君张宴俟雄豪。\n舟人笑指千余客，谁是烟霄六翮毛。",
        "dynasty": "唐",
        "collection_info": {
            "collection": "御定全唐诗",
            "volume": "卷六百零二"
        }
    },
    {
        "uuid": "bee94412f19b9d13f7e14c0c180d701d",
        "title": "干将墓",
        "author": "汪遵",
        "content": "橐钥冰霜万古闻，拍灰松地见余坟。\n应缘神剑飞扬久，水水山山尽是云。",
        "dynasty": "唐",
        "collection_info": {
            "collection": "御定全唐诗",
            "volume": "卷六百零二"
        }
    },
    {
        "uuid": "3c50868e1d7d4c5ed1d57b6ddb607710",
        "title": "易水",
        "author": "汪遵",
        "content": "匕首空磨事不成，误留龙袂待琴声。\n斯须却作秦中鬼，青史徒标烈士名。",
        "dynasty": "唐",
        "collection_info": {
            "collection": "御定全唐诗",
            "volume": "卷六百零二"
        }
    },
    {
        "uuid": "44fde9fc80407d26d2df9f7a4195c87c",
        "title": "鸡鸣曲",
        "author": "汪遵",
        "content": "金距花冠傍舍栖，清晨相叫一声齐。\n开关自有冯生计，不必天明待汝啼。",
        "dynasty": "唐",
        "collection_info": {
            "collection": "御定全唐诗",
            "volume": "卷六百零二"
        }
    },
    {
        "uuid": "1d46b6cfac42484e0b205f6c195a14e0",
        "title": "越女",
        "author": "汪遵",
        "content": "玉貌何曾为浣沙，只图勾践献夫差。\n苏台日夜唯歌舞，不觉干戈犯翠华。",
        "dynasty": "唐",
        "collection_info": {
            "collection": "御定全唐诗",
            "volume": "卷六百零二"
        }
    },
    {
        "uuid": "06f90f67c86fb3f8a64e72ee0f66c1ae",
        "title": "望思台",
        "author": "汪遵",
        "content": "不忧家国任奸臣，骨肉翻为蓦路人。\n巫蛊事行冤莫雪，九层徒筑见无因。",
        "dynasty": "唐",
        "collection_info": {
            "collection": "御定全唐诗",
            "volume": "卷六百零二"
        }
    },
    {
        "uuid": "54e3a0e2ccefb9215a13147098444eff",
        "title": "比干墓",
        "author": "汪遵",
        "content": "国乱时危道不行，忠贤谏死胜谋生。\n一沉冤骨千年后，垄水虽平恨未平。",
        "dynasty": "唐",
        "collection_info": {
            "collection": "御定全唐诗",
            "volume": "卷六百零二"
        }
    },
    {
        "uuid": "0e2f01c991dd7ee663265795c71843c7",
        "title": "北海",
        "author": "汪遵",
        "content": "汉臣曾此作缧囚，茹血衣毛十九秋。\n鹤发半垂龙节在，不闻青史说封侯。",
        "dynasty": "唐",
        "collection_info": {
            "collection": "御定全唐诗",
            "volume": "卷六百零二"
        }
    },
    {
        "uuid": "cefbf082fea3b833cc13255b1e4a9bde",
        "title": "屈祠",
        "author": "汪遵",
        "content": "不肯迂回入醉乡，乍吞忠梗没沧浪。\n至今祠畔猿啼月，了了犹疑恨楚王。",
        "dynasty": "唐",
        "collection_info": {
            "collection": "御定全唐诗",
            "volume": "卷六百零二"
        }
    },
    {
        "uuid": "eb124ef6210939148bd5da5d007e3fc9",
        "title": "战城南",
        "author": "汪遵",
        "content": "风沙刮地塞云愁，平旦交锋晚未休。\n白骨又沾新战血，青天犹列旧旄头。",
        "dynasty": "唐",
        "collection_info": {
            "collection": "御定全唐诗",
            "volume": "卷六百零二"
        }
    },
    {
        "uuid": "1310b8530064099b414b62af44829530",
        "title": "招隐",
        "author": "汪遵",
        "content": "罢听泉声看鹿群，丈夫才策合匡君。\n早携书剑离岩谷，莫待蒲轮辗白云。",
        "dynasty": "唐",
        "collection_info": {
            "collection": "御定全唐诗",
            "volume": "卷六百零二"
        }
    },
    {
        "uuid": "694bcf66faac8557ed82a0431d7de132",
        "title": "渑池",
        "author": "汪遵",
        "content": "西秦北赵各称高，池上张筵列我曹。\n何事君王亲击缶，相如有剑可吹毛。",
        "dynasty": "唐",
        "collection_info": {
            "collection": "御定全唐诗",
            "volume": "卷六百零二"
        }
    },
    {
        "uuid": "05dce836e54ae9ed0eace75a4e5f4da0",
        "title": "咏酒二首",
        "author": "汪遵",
        "content": "九酝松醪一曲歌，本图闲放养天和。\n后人不识前贤意，破国亡家事甚多。\n万事销沈向一杯，竹门哑轧为风开。\n秋宵睡足芭蕉雨，又是江湖入梦来。",
        "dynasty": "唐",
        "collection_info": {
            "collection": "御定全唐诗",
            "volume": "卷六百零二"
        }
    }
]