[
    {
        "uuid": "3aa930510f4adb902748dd128f9c4124",
        "title": "輓吕东莱  其一",
        "author": "康文虎",
        "content": "中兴以后谁堪数，名满东南震昔贤。\n旧论当时存喘息，微波今日塞天渊。\n承平格力回全盛，人物风流继往年。\n太息何人知所自，此心时復一潸然。",
        "dynasty": "宋",
        "collection_info": null
    },
    {
        "uuid": "5f9e46ebcd8b36841f4491cc7460a685",
        "title": "輓吕东莱  其二",
        "author": "康文虎",
        "content": "国尚有人悲此老，天其丧我泣吾曹。\n平生心事知谁与，怅望今人论太高。\n便欲卑心随故步，岂期中路丧连鳌。\n先生已死吾何望，举眼犹知有凤毛。",
        "dynasty": "宋",
        "collection_info": null
    }
]