[
    {
        "uuid": "83084074f32a061fc6e4185b0ff49676",
        "title": "舟行江上",
        "author": "方汝疆",
        "content": "平林漠漠暝烟齐，竹树萧疏望眼迷。\n相唤几声何处雁，断霞明处一行低。",
        "dynasty": "宋",
        "collection_info": null
    },
    {
        "uuid": "5bfac011c971d357eae908f6b5b8ecc7",
        "title": "江上晚行",
        "author": "方汝疆",
        "content": "疏云薄日冷吴江，江色芦花共渺茫。\n四五点山烟霭淡，两三枝桨水云长。\n游鱼避网惊微浪，幽鹭窥汀下夕阳。\n兴罢归来更回首，满身明月踏溪霜。",
        "dynasty": "宋",
        "collection_info": null
    },
    {
        "uuid": "67d157d3f234c62fc694af2016eed354",
        "title": "江上晚望",
        "author": "方汝疆",
        "content": "柳边茅舍倚渔矶，沙上轻禽贴水飞。\n千顷夕阳秋练浄，谁家一叶晚来归。",
        "dynasty": "宋",
        "collection_info": null
    }
]