[
    {
        "uuid": "e41df1196bcf0fe0a9cae6ac1255526d",
        "title": "水调歌头 把酒对湘浦",
        "author": "马廷鸾",
        "content": "把酒对湘浦，独吊大夫醒。\n当年皇览初度，饮露更餐英。\n服以高冠长佩，扈以江蓠薜芷，御气独乘清。\n谁意椒兰辈，从臾武关盟。\n哭东门，哀郢路，悄无宁。\n人世纷纷起灭，遗臭与留馨。\n一笑还游轻举，三叹道长世短，晦朔自秋春。\n洗眼看物变，朝菌共灵椿。",
        "dynasty": "宋",
        "collection_info": null
    },
    {
        "uuid": "1387152cf490959743a912054c82a71f",
        "title": "齐天乐 老夫耄矣",
        "author": "马廷鸾",
        "content": "老夫耄矣，怪新年顿尔，□衰俱现。\n排闷篇诗，浇愁盏酒，自读离骚自劝。\n长安日远。\n怅旧国禾宫，故侯瓜畹。\n风景不殊，江涛如此世缘浅。\n莫莫休休□□，□□干坤毁，幽怀无限。\n弱羽填波，轻装浮海，其奈沧溟潋滟。\n年华婉娩。\n况六十平头，底须顽健。\n戏唱高词，作还丹九转。",
        "dynasty": "宋",
        "collection_info": null
    },
    {
        "uuid": "0ccbf69894766b6d53c26638bcf2bdd5",
        "title": "沁园春 杨柳依依",
        "author": "马廷鸾",
        "content": "杨柳依依，我生之辰，与公共之。\n叹袅娜章台，歌翻轻吹，飘零灞岸，影弄斜晖。\n花萼楼深，灵和殿古，人自凄凉柳自垂。\n相逢处，记吾侬坠地，嘉定明时。\n何须梦得君知。\n便稳道人生七十稀。\n笑桓大将军，枝条如此，陶潜处士，门巷归兮。\n几阵花飞，一池萍碎，又向先生把寿卮。\n年年好，祝东风万楼，老翠云齐。",
        "dynasty": "宋",
        "collection_info": null
    },
    {
        "uuid": "61be072c1d2020a3276a4e8091e3d325",
        "title": "水调歌头 老子早知退",
        "author": "马廷鸾",
        "content": "老子早知退，鸥鹭未盟寒。\n痴顽逾六望七，宁以寿为欢。\n风有黍离伤咽，雅有蓼莪憔悴，使我不能餐。\n更把南陔读，泪落广陵澜。\n踏峨峰，腾华顶，卧王宫。\n青山与汝卒岁，紫茹可登盘。\n乞得白翁归处，莫学缁郎更误，危梦倚栏干。\n多谢长生曲，颜面怕人看。",
        "dynasty": "宋",
        "collection_info": null
    },
    {
        "uuid": "52bc2fd948cd29e4f1dd9f3a86e6e2ff",
        "title": "失调名 东晋纤儿撞坏",
        "author": "马廷鸾",
        "content": "东晋纤儿撞坏，桑令人间受祸。",
        "dynasty": "宋",
        "collection_info": null
    },
    {
        "uuid": "876d2fb3b79987c69c881d7ca6dc48d0",
        "title": "馆中送郑着作",
        "author": "马廷鸾",
        "content": "士为慾心缚，蜗牛粘壁枯。\n荣华不盈睫，咎责弥八区。\n不有君子人，中流谁一壶。\n公怀天台秋，夙昔廊庙须。\n南宫接东观，并辔骖天衢。\n幽忧肠内热，慷慨涕濡缕。\n拜疏上虚皇，诵言折姦愚。\n肝脑非己物，宇宙须人扶。\n恭惟天王圣，肯使善类孤。\n一朝拥麾盖，自诡歌袴襦。\n黟歙股肱郡，新安文物都。\n斯文紫阳翁，千载长昭苏。\n稻苗新进士，倚公为播敷。\n茧丝困穷民，愿公荐蒍于。\n勉哉崇明德，归来诵唐虞。",
        "dynasty": "宋",
        "collection_info": null
    },
    {
        "uuid": "a8d29d88b580391e89c435fd2c0adfe5",
        "title": "皇太子生辰诗三首  其一",
        "author": "马廷鸾",
        "content": "煌煌炎宋兴，奕世开燕谋。\n建隆圣人出，庚年宝运周。\n祥符帝子生，巳月神光流。\n稽首颂储君，昭哉遹嘉猷。\n吹铜协干阳，主鬯弥千秋。\n星晖狼弧低，海润青齐收。\n金轮整鹤驾，玉觞侍龙楼。\n无逸能为寿，干干谨时休。",
        "dynasty": "宋",
        "collection_info": null
    },
    {
        "uuid": "7cd4ebc7330f1e6d9638565a35ebcfb2",
        "title": "皇太子生辰诗三首  其二",
        "author": "马廷鸾",
        "content": "苍龙见天东，房驷拱辰北。\n煌煌心星前，炳炳天王侧。\n休符协干文，正阳毓紫极。\n铜楼蔼祥光，玉巵奉愉色。\n叹声沸笙鸾，寿龄指箕翼。\n何以祝元良，勉哉崇明德。\n学问日就将，福禄时万亿。\n永侍帝宸尊，重晖照四国。",
        "dynasty": "宋",
        "collection_info": null
    },
    {
        "uuid": "fe3ba0cd2ed4862be4385920c56629b7",
        "title": "皇太子生辰诗三首  其三",
        "author": "马廷鸾",
        "content": "正阳毓前星，盛事符仁祖。\n仁者寿之基，生意一何溥。\n欢愉侍宫庭，晖润弥海宇。\n三朝谨师文，寸阴勤惜禹。\n新功鑑铭盘，妙用明絜矩。\n嘉宾从商园，末僚愧韩愈。\n永言祝储君，重离日常午。\n八表跻春台，万年受天祜。",
        "dynasty": "宋",
        "collection_info": null
    },
    {
        "uuid": "86df300be1e4acfbedca322ccdcac83c",
        "title": "用大东莱临川诗韵示诸儿",
        "author": "马廷鸾",
        "content": "惠子五车书，彼富吾何慊。\n滔滔岁峥嵘，濯濯木荏苒。\n前荣悼虚夸，新懦就退敛。\n东邻有硕师，簦箧孰云远。\n斯文岂终穷，小子宜黾勉。\n寒檠炷老膏，此兴復不浅。",
        "dynasty": "宋",
        "collection_info": null
    },
    {
        "uuid": "833f052ab7604fcd5944d1df7edd6bec",
        "title": "次韵周公谨见寄  其一",
        "author": "马廷鸾",
        "content": "十年思美人，渊沦抑天飞。\n辛勤种青门，竟作抱蔓归。\n日月老宾送，霜露沾人衣。\n沾衣何足云，八表笼烟霏。",
        "dynasty": "宋",
        "collection_info": null
    },
    {
        "uuid": "c7905b2854c6154404fe99a34ca8220e",
        "title": "次韵周公谨见寄  其二",
        "author": "马廷鸾",
        "content": "空山学仙子，满耳笙箫听。\n谁知九天上，云扉本不扃。\n度世同御风，蓬蓬随飘零。\n又如芬陀花，出火而青青。",
        "dynasty": "宋",
        "collection_info": null
    },
    {
        "uuid": "d73637025f44c3c187488bf47b3470fa",
        "title": "次韵周公谨见寄  其三",
        "author": "马廷鸾",
        "content": "涪翁雪堂仙，分谊故不疎。\n投之孤芳篇，托根岂云虚。\n报以蟠桃实，一尝千载余。\n洗髓蹑阆苑，游于物之初。",
        "dynasty": "宋",
        "collection_info": null
    },
    {
        "uuid": "53b18237d025c0898f8c165353c47cad",
        "title": "次韵周公谨见寄  其四",
        "author": "马廷鸾",
        "content": "射洪高蹈翁，哀歌泪盈盈。\n幽居观元化，悼此岁月更。\n感遇三十篇，读之慨余情。\n白露号玄蝉，春日鸣仓庚。",
        "dynasty": "宋",
        "collection_info": null
    },
    {
        "uuid": "efc4dd64a7b866cd2c426b1d2e3da989",
        "title": "次韵周公谨见寄  其五",
        "author": "马廷鸾",
        "content": "退之怀桂林，药物珍陆离。\n物情恶衰歇，义心感亲知。\n我生欠一死，不死当语谁。\n与我制颓龄，悠悠白云期。",
        "dynasty": "宋",
        "collection_info": null
    },
    {
        "uuid": "cdd5d8b398c0d2cd769396e1e2ae710f",
        "title": "题王氏琴清堂",
        "author": "马廷鸾",
        "content": "孤桐缺月风露秋，夜虫催织寒飕飗。\n拂床文字翻叶叶，古心埋没从何求。\n客来洗予筝笛耳，清圜琅然散百忧。\n南窗无絃鼓愈淡，焦尾有桐弃不收。\n卓哉奇士千载去，已矣奇弄万古休。\n江左诸王孙子俦，琴清之堂遗风流。\n飞泉爽籁十二操，铿锵浮玉鸣天球。\n文王宣父次第作，此身还见大雅不。\n收拾书囊杂钓具，伴君携琴隠林丘。\n作诗一为写奇趣，此生此兴长悠悠。",
        "dynasty": "宋",
        "collection_info": null
    },
    {
        "uuid": "8ae7c9974c3cb2a4d254d9e58169d2dd",
        "title": "次韵谢洁斋惠春膏纸",
        "author": "马廷鸾",
        "content": "霜毫秃尽千枝竹，铜雀台荒死潘谷。\n哀哉四宝併成空，犹有老崖藤捣玉。\n青钱学士将相科，黑头刺史朱丹毂。\n怀银早去镇湖湘，掞藻端如起巴蜀。\n天乎岁晚椓斯文，往往长吟书短幅。\n云昏雨暗白龙笺，林密山深紫芝曲。\n凤楼谁助斧斤修，鱼网不禁尘土辱。\n我驰家畔楮先生，越薄吴腴此粗俗。\n铿金戛玉新有声，缝雾裁云岂堪录。\n向来交友文字间，矢往湍奔如撒菽。\n薄材那敢派江西，一寸诗肠愁万斛。",
        "dynasty": "宋",
        "collection_info": null
    },
    {
        "uuid": "e7ce2602b9b74a6ddb8d03ed657eb7c2",
        "title": "次韵汤叔逊谢笔墨长句",
        "author": "马廷鸾",
        "content": "南屏翁，斯文千古何终穷，清辉灵气斗牛充。\n我从公家二老话此事，寒更支坐烛跋红。\n哀哉人琴俱亡天地覆，有刀有玉谁错礲。\n翁今岿然鲁灵殿，砥柱一叶万仞中。\n朅来访我维摩室，我起于坐欣迎公。\n惊呼绝嘆吾道厄，客卿颖士委蒿蓬。\n竈煤苇管不足用，宣城黟水无良工。\n奈何盲卒乘钝马，欲写杰作称词雄。\n赠公撒雷挥电施敏手，余事渲染文字如飞虫。\n我生哀伤所欠死，十年破砚烟雨蒙。\n一朝洗眼获玉句，金膏水碧浸方瞳。\n翰墨场中身老大，期公盛气晚霞同。\n峥嵘素论犹激烈，始信迂儒曲学如发蒙。",
        "dynasty": "宋",
        "collection_info": null
    },
    {
        "uuid": "fc48b0037e2dbef56e324714a01fad4f",
        "title": "谢吴直卿惠嘉树篇",
        "author": "马廷鸾",
        "content": "槐底婆娑生意尽，柳边摇落长年悲。\n殷东阳守徒嗟惜，桓大将军自涕洟。\n不知庾叟江潭赋，何似延陵季子诗。",
        "dynasty": "宋",
        "collection_info": null
    },
    {
        "uuid": "f891a66d0cdd1e0c1f438ef749146cd4",
        "title": "次赵二车韵",
        "author": "马廷鸾",
        "content": "世事真如此，劳生何所知。\n功名蚁行磨，意气鹊栖枝。\n于蒍歌偏好，归来赋足师。\n达人宁自苦，天乐更无疑。",
        "dynasty": "宋",
        "collection_info": null
    },
    {
        "uuid": "2b60371789adba0510b459280995d6cb",
        "title": "次李改卿韵",
        "author": "马廷鸾",
        "content": "丽句费敲推，清吟出竞病。\n日长简编丛，春老蓬蒿径。\n志士苦忧时，高人思缮性。\n山房读道书，晚花红艷静。",
        "dynasty": "宋",
        "collection_info": null
    },
    {
        "uuid": "6f676900e4b3fc2af200de237a1b1b6f",
        "title": "恭进理宗皇帝挽词  其一",
        "author": "马廷鸾",
        "content": "仁孝初闻代，讴歌早戴虞。\n多能天与圣，大度祖同符。\n恻怛钦刑诏，严恭事帝图。\n初终两甲子，经远有宏模。",
        "dynasty": "宋",
        "collection_info": null
    },
    {
        "uuid": "f9e6bb44db6392844e0a8a2b913f9332",
        "title": "恭进理宗皇帝挽词  其二",
        "author": "马廷鸾",
        "content": "典学怀终始，熈明四十年。\n立心天地厚，接统帝王前。\n舄奕临雍礼，昭回赞道篇。\n古今惟理大，尊号冠瑶编。",
        "dynasty": "宋",
        "collection_info": null
    },
    {
        "uuid": "dbb845d0ef4cfd2fbd3fdb485589c575",
        "title": "恭进理宗皇帝挽词  其三",
        "author": "马廷鸾",
        "content": "天保惟勤政，春秋有復雠。\n园陵初谒汉，境土合归周。\n连海沧波静，长江兵祲收。\n庚申重立极，功与建隆侔。",
        "dynasty": "宋",
        "collection_info": null
    },
    {
        "uuid": "c208e8e0cb02ea238b806176d0dc7cf0",
        "title": "恭进理宗皇帝挽词  其四",
        "author": "马廷鸾",
        "content": "神册方增授，龙髯遽莫攀。\n千秋思沛邑，七月葬稽山。\n春暗觚棱影，星回羽卫班。\n寝门如昨日，无復侍威颜。",
        "dynasty": "宋",
        "collection_info": null
    },
    {
        "uuid": "2e1b65ccdf5ff58ab18781c3282c203b",
        "title": "恭进理宗皇帝挽词  其五",
        "author": "马廷鸾",
        "content": "尽拜宸奎赐，新编圣训成。\n孙谋方燕翼，龙驭忽遐征。\n四海尧音密，三年舜慕情。\n因山图固在，合应若神明。",
        "dynasty": "宋",
        "collection_info": null
    },
    {
        "uuid": "53b43cb5896a09bbad3280a5c9395ab4",
        "title": "十月二十六日甲子",
        "author": "马廷鸾",
        "content": "乘云伤往岁，甲子又今晨。\n莫唱贞元曲，谁为宝庆人。\n早霜明带月，寒菊艷争春。\n敢睨昭陵柏，僞呵有鬼神。",
        "dynasty": "宋",
        "collection_info": null
    },
    {
        "uuid": "e20d1131c84c0596d9afd783403ac654",
        "title": "赠汪泰轩",
        "author": "马廷鸾",
        "content": "万言朝凤阙，一笑落渔舟。\n把我葱珩解，从公款段游。\n东来迎羽服，西去羡羊裘。\n挥手谢汉使，蒲轮公所羞。",
        "dynasty": "宋",
        "collection_info": null
    },
    {
        "uuid": "6f413de19893bf033be5fab2bdd12ecd",
        "title": "久雨潦涨未已",
        "author": "马廷鸾",
        "content": "一雨遂踰月，连朝仍彻宵。\n雷公自收麦，田父不耘苗。\n时见危垣堕，仍闻比屋漂。\n愧无援溺手，穷巷有持桡。",
        "dynasty": "宋",
        "collection_info": null
    },
    {
        "uuid": "aeec9c9b7fc77ea59a9a6cb6d6feff09",
        "title": "恭进度宗皇帝挽词  其一",
        "author": "马廷鸾",
        "content": "四闰临朝浅，羣生被泽深。\n俭勤成禹圣，仁孝本虞心。\n汉殿觞称玉，轩湖鼎铸金。\n龙髯攀不得，清血但盈襟。",
        "dynasty": "宋",
        "collection_info": null
    },
    {
        "uuid": "4128bfa4958e01bf6d9e848bef106b9c",
        "title": "恭进度宗皇帝挽词  其二",
        "author": "马廷鸾",
        "content": "道远年何驶，民肥身独癯。\n宝龟传圣子，玉几导宸谟。\n百世尊王度，千秋拱帝图。\n孤臣惭舜辅，愁绝望苍梧。",
        "dynasty": "宋",
        "collection_info": null
    },
    {
        "uuid": "5ca6515d9b2dab4b0e1cf5d851750810",
        "title": "答赵心游与梭",
        "author": "马廷鸾",
        "content": "亦有猗那颂，从谁说象贤。\n振振麟趾族，煜煜锦袍仙。\n礼乐三雍对，神明百世传。\n王孙何处隠，芳草自连天。",
        "dynasty": "宋",
        "collection_info": null
    },
    {
        "uuid": "0580b517f03a0d242c274d9f064e7b8b",
        "title": "程楚翁访考亭旧居着闽山集为题其后",
        "author": "马廷鸾",
        "content": "有客传吟藁，知渠来自闽。\n四书犹在鲁，六籍不忧秦。\n太史经邹峄，离骚感楚臣。\n谁知梦奠日，曾忆后庚申。",
        "dynasty": "宋",
        "collection_info": null
    },
    {
        "uuid": "98c895fa914dae8f0e2033bb1221fdcf",
        "title": "挽李楼峰  其一",
        "author": "马廷鸾",
        "content": "万选胶庠上，三长渠观中。\n端从绣衣使，直拟黑头公。\n柯烂全枰换，舟移绝壑空。\n素交与年尽，老眼视天梦。",
        "dynasty": "宋",
        "collection_info": null
    },
    {
        "uuid": "80f508dc3da6d6ba370f890f28c77151",
        "title": "挽李楼峰  其二",
        "author": "马廷鸾",
        "content": "短椠传边警，长篇罄亩忠。\n危邦韬昼锦，剧盗剪春葱。\n地隔几庐舍，天怜两秃翁。\n而今吾后死，作传岂能工。",
        "dynasty": "宋",
        "collection_info": null
    },
    {
        "uuid": "54a4359975385451eff458bad18599f6",
        "title": "挽徐朝奉  其一",
        "author": "马廷鸾",
        "content": "海内嗟遗老，诸公表逸民。\n过庭忠训在，攀槛直声新。\n谏草频尊主，绯花与显亲。\n一门名父子，千载庆君臣。",
        "dynasty": "宋",
        "collection_info": null
    },
    {
        "uuid": "85feaeca3c084f16e2fcb4a62f7fc9a6",
        "title": "挽徐朝奉  其二",
        "author": "马廷鸾",
        "content": "儿罢金华讲，翁从林下归。\n清时伯夷粟，愉色老莱衣。\n洛社风流在，襄阳耆旧稀。\n泷冈有名笔，字字独幽辉。",
        "dynasty": "宋",
        "collection_info": null
    },
    {
        "uuid": "196e556dfddfedaf4d44850df48ad3d1",
        "title": "次韵洁堂五日",
        "author": "马廷鸾",
        "content": "故国天中节，吾侪日暮年。\n愁心菖歜苦，悲绪綵丝牵。\n迭雪虚唐赐，熏风绝舜絃。\n穷山饤越果，醉摘尚凄然。",
        "dynasty": "宋",
        "collection_info": null
    },
    {
        "uuid": "da96a81cb05833696437b0b8df150631",
        "title": "挽费洁堂  其一",
        "author": "马廷鸾",
        "content": "井络璠玙瑞，江干英簜驰。\n万屯孤宿饱，一旅共时危。\n行地嗟蓬转，呼天泣黍离。\n百年公有尽，一恸我非私。",
        "dynasty": "宋",
        "collection_info": null
    },
    {
        "uuid": "988c6546b31b39559d7034828bee8126",
        "title": "挽费洁堂  其二",
        "author": "马廷鸾",
        "content": "共事咸淳帝，俱生嘉定年。\n江湖正寥阔，梁楚忽姻连。\n不作武担掾，翻成葛水仙。\n岂忘渠剑阁，来闭此荒阡。",
        "dynasty": "宋",
        "collection_info": null
    },
    {
        "uuid": "142fa5da5a084a71edbd6a4afe909ed9",
        "title": "挽陈本斋",
        "author": "马廷鸾",
        "content": "擢第韩欧上，论交涧浦边。\n声名宁我后，官职逊人先。\n徐广生多戚，龚宾死独贤。\n拊膺前劫事，雪涕大招篇。",
        "dynasty": "宋",
        "collection_info": null
    },
    {
        "uuid": "88846c0ecffa4a0c030d2d6489855fe9",
        "title": "赠程楚翁",
        "author": "马廷鸾",
        "content": "汗竹丹铅侧，空花粉黛中。\n尚怀丞相亮，肯署大夫雄。\n有客来今雨，夸予迈古风。\n幽情倾不竭，渺渺碧云东。",
        "dynasty": "宋",
        "collection_info": null
    },
    {
        "uuid": "5a09f6406ca5e207a53a9a00a8eea03e",
        "title": "恭进明堂大礼庆成诗",
        "author": "马廷鸾",
        "content": "鉅典崇邦祀，精禋展国阳。\n泰元神授筴，癸亥日宣光。\n艺祖郊天始，高皇受命长。\n后庚基再造，先甲迓殊祥。\n率育歌时夏，仪刑咏我将。\n天街澄析木，农扈庆金穰。\n筑塞惩獯鬻，梯山谢越裳。\n宗祈严美报，亲享荐嘉尝。\n周士咸奔走，尧民共颂扬。\n青冥收夕雨，华耀炳朝阳。\n月御金波穆，星流珠幄黄。\n九重纷羽卫，十二驾龙骧。\n鋗玉琳琅展，轩朱磬管锵。\n时行肃天步，安坐集神鴹。\n圣孝昭初祼，元良俨贰觞。\n旗常森妸娜，黼黻罢周张。\n柴燄千灵堕，兰膏百末香。\n金鸡初日丽，丹凤德风翔。\n薄海干施博，垂云解泽滂。\n批周仍蹋晋，蹴汉亦超唐。\n臣浅来蓬户，君仁点玉堂。\n恩书容稿进，嘉颂媿辞荒。\n有道帝能享，难谌圣敢康。\n畏威勤夙夜，万寿祝君王。",
        "dynasty": "宋",
        "collection_info": null
    },
    {
        "uuid": "1627654b8a692d7b69ebda4c50482f5e",
        "title": "恭和御制诗  其一",
        "author": "马廷鸾",
        "content": "圣作巍巍泰华高，淋漓赐笔洒春膏。\n奎文河汉天垂象，藻思波澜海驾鳌。\n淳化罕逢休叹昉，大中亲遇不夸绹。\n骊珠数十光盈把，何啻春秋一字褒。",
        "dynasty": "宋",
        "collection_info": null
    },
    {
        "uuid": "4d2d0587e8d165967d8cfba2165d1521",
        "title": "恭和御制诗  其二",
        "author": "马廷鸾",
        "content": "直庐峻在九霄高，雨露恩光切仰膏。\n夜炬恩浓超赐锦，春船思涩怯提鳌。\n日砖有影占花隠，风铎无声引索绹。\n昭代崇儒逢圣主，小臣待诏愧王褒。",
        "dynasty": "宋",
        "collection_info": null
    },
    {
        "uuid": "30b3f818d742cc4971b7efd954f6553a",
        "title": "恭和御制赐进士韵",
        "author": "马廷鸾",
        "content": "熈朝道化聿求成，龙衮天临策俊英。\n清问详延敷乃听，嘉犹入告底于行。\n尧章焜耀欣承渥，汤训丁宁戒近名。\n圣主得贤功烈盛，小臣稽首愿升平。",
        "dynasty": "宋",
        "collection_info": null
    },
    {
        "uuid": "59295a1d01f39856dc465ed7d23ad61a",
        "title": "御书道山堂次林竹溪韵",
        "author": "马廷鸾",
        "content": "芒玉平云玺印红，洛龟图画五三隆。\n壁奎星聚来时彦，河汉天垂仰化工。\n文治正应淳化似，恩华重与绍兴同。\n何须飞白人人赐，始悟君王欲教忠。",
        "dynasty": "宋",
        "collection_info": null
    },
    {
        "uuid": "3813d0b6d1d4d6cd31c4f79c5d71f443",
        "title": "十月二十日客有言儒学事感而有赋",
        "author": "马廷鸾",
        "content": "大中之后建隆前，鱼烂瓜分且百年。\n地闢天开崇帝学，河辉斗灿动星躔。\n千龄必反人弘道，一念潜通圣即天。\n叹息斯文今有幸，昭昭奎运岂徒然。",
        "dynasty": "宋",
        "collection_info": null
    },
    {
        "uuid": "918e9c0b02b56b848db2be2747194a1e",
        "title": "和南塘叔赏芙蓉韵",
        "author": "马廷鸾",
        "content": "自携败册小窗开，三十头颅四十来。\n閒日诗书真足味，熏天富贵只飞灰。\n怜渠每吸醋三斗，输我清余水一杯。\n何似山翁醉花下，安排笾豆洗樽罍。",
        "dynasty": "宋",
        "collection_info": null
    },
    {
        "uuid": "39da26c4f624849b8f13eb896fcb1c73",
        "title": "双鹤",
        "author": "马廷鸾",
        "content": "荒塘水竭只蹄涔，双鹤翩然啄午阴。\n此纵有鱼应渴死，不濡其咮漫窥临。\n病鸱尚畏泥坑辱，宿鸟常虞矰缴侵。\n何似舂锄甘寂寞，一滩藻荇立清深。",
        "dynasty": "宋",
        "collection_info": null
    },
    {
        "uuid": "21ca3ec6e4eb6e88ae6df1beda520a94",
        "title": "送建康知录操襟兄",
        "author": "马廷鸾",
        "content": "虎鞯尚落诸贤后，鴈塔谁知几榜前。\n尽向心田宽地步，却将官职信天缘。\n难忘旧日钟山阁，易趁东风上水船。\n王谢诸人英烈在，问今何策可筹边。",
        "dynasty": "宋",
        "collection_info": null
    },
    {
        "uuid": "4194d926431430a84e649e839f12e538",
        "title": "送汤东涧出守南剑州  其一",
        "author": "马廷鸾",
        "content": "掉头不肯住清都，勇趁秋风乞左符。\n大论峥嵘耸廊庙，雅怀磊落胜江湖。\n丹心岂不恋明主，清节还能立懦夫。\n正是商山访鸿鹄，归来羽翼莫踟蹰。",
        "dynasty": "宋",
        "collection_info": null
    },
    {
        "uuid": "f66f9476ca965317a3d905b25821ca23",
        "title": "送汤东涧出守南剑州  其二",
        "author": "马廷鸾",
        "content": "七聚名藩亦甚都，龙津剑气正扶舆。\n斯文孰是南夫子，此地重逢行秘书。\n忠爱平生在宗社，叹愁肯使到田闾。\n黄花粲粲牵归兴，岁晚江空一怅如。",
        "dynasty": "宋",
        "collection_info": null
    },
    {
        "uuid": "36f3d9d20ef85808f878a25119fd4b81",
        "title": "秘省和刘左司韵",
        "author": "马廷鸾",
        "content": "三年三揖壁奎星，当日曾登着作庭。\n大雅重逢君子聚，斯文还属圣人兴。\n倚天延阁缘云上，拔地方壶历级升。\n自别青藜仙分隔，借书独对短檠灯。",
        "dynasty": "宋",
        "collection_info": null
    },
    {
        "uuid": "228385dff4b5635994236279976ee239",
        "title": "病中修实录",
        "author": "马廷鸾",
        "content": "明圣当阳四十春，十年供奉感孤臣。\n云龙幄幙天容迩，河汉篇章帝墨新。\n正始遗音危绝缕，贞元旧曲恸沾巾。\n焚膏痛记乌号旦，目断稽山欲叫旻。",
        "dynasty": "宋",
        "collection_info": null
    },
    {
        "uuid": "6ed88b06ac5898c89261bda7acaa2927",
        "title": "秋雨叹",
        "author": "马廷鸾",
        "content": "夜夜黄昏雨打窗，愁霖久矣晦明阳。\n天公一怒四山黑，田父三吁百亩黄。\n禾黍油油生有耳，芭蕉点点断无肠。\n病身更与儿俱懒，墙角全抛风露凉。",
        "dynasty": "宋",
        "collection_info": null
    },
    {
        "uuid": "1d58cb88e10fff124266ff54a4bb0686",
        "title": "久雨遣饷王新班",
        "author": "马廷鸾",
        "content": "舍南舍北水漫漫，乍霁仍阴暖復寒。\n石补色天原有漏，泥污后土不曾干。\n龙蛇起陆生光怪，鸾凤翀霄怯羽翰。\n聊復盘餐饷桑户，可能藜杖过苏端。",
        "dynasty": "宋",
        "collection_info": null
    },
    {
        "uuid": "f810471a529e5dca070dcf4ca4b45601",
        "title": "十月望日泛舟鹅塘感坡翁后赤壁赋有作",
        "author": "马廷鸾",
        "content": "浮浮短艇水风微，一枕清溪遶曲崎。\n篷底镕金斜日碎，天边散绮暮霞飞。\n霜凝水落黄泥坂，月小山高赤壁矶。\n等是初冬一风景，感今怀昔自歔欷。",
        "dynasty": "宋",
        "collection_info": null
    },
    {
        "uuid": "ae02409df1db1b2132fcd9113c133621",
        "title": "二儿就试",
        "author": "马廷鸾",
        "content": "老病吾今业已衰，已还魏笏尚支颐。\n祝儿指日传金榜，怀我当年别玉墀。\n殿陛详延方吁俊，江湖空旷剧忧时。\n此行蹇谔论邦国，莫为区区杏苑诗。",
        "dynasty": "宋",
        "collection_info": null
    },
    {
        "uuid": "79dad235426cc0df98beeb1a6cf1b6d4",
        "title": "后中秋",
        "author": "马廷鸾",
        "content": "金风吹彻玉箫寒，志士悲秋思万端。\n千古凄凉更余闰，百年圆缺又重看。\n清辉照胆浑无寐，苍昊催人自鲜欢。\n斗酒属公今夜看，只亏些子莫长嘆。",
        "dynasty": "宋",
        "collection_info": null
    },
    {
        "uuid": "57bb9301f012439aabf6e3136cb2183d",
        "title": "次吴园亲友韵",
        "author": "马廷鸾",
        "content": "乞得危身百尺竿，冥心晦息掩柴关。\n自寻别墅开荒径，忽见高轩厌辔环。\n海宇泬寥黄鹄举，风涛浩荡白鸥閒。\n剑花落尽长堤圮，叹息英雄隠此山。",
        "dynasty": "宋",
        "collection_info": null
    },
    {
        "uuid": "9418a0edf89ade9fd189e0785860fb22",
        "title": "癸酉春暮钟信甫寄诗次其韵  其一",
        "author": "马廷鸾",
        "content": "深闭柴门水竹村，是非荣辱总忘言。\n舍生只惧本心失，犯患谁知尊足存。\n居士病来惟卧室，翟公客去莫书门。\n人心日月无今古，世道何曾顷刻昏。",
        "dynasty": "宋",
        "collection_info": null
    },
    {
        "uuid": "3adcef447b656c47cfb991c30081fb5e",
        "title": "癸酉春暮钟信甫寄诗次其韵  其二",
        "author": "马廷鸾",
        "content": "精诚可使岳云开，浊世狂澜挽不回。\n苍狗白衣从物变，青山流水唤人来。\n交游莫作宣明面，气燄终成内史灰。\n我有长波一归艇，枕书春睡兴悠哉。",
        "dynasty": "宋",
        "collection_info": null
    },
    {
        "uuid": "1f05f363565ee25839972e2a916c2819",
        "title": "次胡玉叟韵",
        "author": "马廷鸾",
        "content": "莫学前人索送诗，我无姱节可提撕。\n忍听世上新翻曲，堪笑山中老古锥。\n人境炎凉过驹隙，天边日夜走蟾规。\n穷阎又度纯坤月，谁识初阳变一奇。",
        "dynasty": "宋",
        "collection_info": null
    },
    {
        "uuid": "85e2c07095622b04c754d32dbe532ae8",
        "title": "和许伯修韵",
        "author": "马廷鸾",
        "content": "秋风孤愤只心知，接得诗筒为色怡。\n句眼独参成佛后，吟肩耸彻欲仙时。\n俗衰竞觅胡奴饱，节在何妨臣朔饥。\n此话只今谁举似，趋时言语正如巵。",
        "dynasty": "宋",
        "collection_info": null
    },
    {
        "uuid": "de691a51337d7a84f990c4e4abced439",
        "title": "夜病",
        "author": "马廷鸾",
        "content": "幻身危抱十年病，青眼俄成一旦昏。\n夜席何常卧尊者，晨炊不拟饭王孙。\n蜗涎有几春潮涌，鷄唱无凭晓日暾。\n惟有阿枢痴不去，几回惊起问家尊。",
        "dynasty": "宋",
        "collection_info": null
    },
    {
        "uuid": "981b01d6ba2dd8726a51b81c01b0f52e",
        "title": "游荷溪西禅寺",
        "author": "马廷鸾",
        "content": "髣髴招提寄远村，缁郎草草佛灯昏。\n水将绿遶萦如带，山送青来列在门。\n句裏风骚耆旧远，胸中丘壑典刑存。\n满怀孤愤几株石，欲起当年两达尊。",
        "dynasty": "宋",
        "collection_info": null
    },
    {
        "uuid": "ec489c2f0a0608d36f3eafa6f677fd14",
        "title": "三月初四夜宿僧庐",
        "author": "马廷鸾",
        "content": "风雨萧萧夜未央，呼童襥被宿僧房。\n无肠可断啼鹃苦，有喙皆鸣吠蛤忙。\n七岁遗孤今老大，百年远忌足悲伤。\n司晨唤起窗全曙，归命清都炷瓣香。",
        "dynasty": "宋",
        "collection_info": null
    },
    {
        "uuid": "e92adf9f465052ba0ca5b002b2aec5f4",
        "title": "次费洁堂韵",
        "author": "马廷鸾",
        "content": "谁翻溟渤倒天瓢，大地山河等呴漂。\n九陌扬尘京路暗，一声鸣鵙楚魂招。\n归心猛折湖边柳，活计频寻江上苗。\n回首神皋双泪落，孤烟斜日短长桥。",
        "dynasty": "宋",
        "collection_info": null
    },
    {
        "uuid": "83e898221685390f714d7415a93d3833",
        "title": "三月初五日先秘阁忌",
        "author": "马廷鸾",
        "content": "鸟啼花落暮春天，一遇斯晨一泫然。\n旧业岂无书可读，遗言犹有石堪传。\n孝思不碍飞遐想，忠愤何由竭报缘。\n庙社已同缨绂尽，尊尧千古忆陈编。",
        "dynasty": "宋",
        "collection_info": null
    },
    {
        "uuid": "c9a13cb7df9c0bb259dacf41f61511fd",
        "title": "秋谒屺瞻墓",
        "author": "马廷鸾",
        "content": "了知五十六年非，何处空山叫阿㜷。\n斗酒隻鸡双泪落，荒林宿莽九原悲。\n黄花委地伤徂岁，青笋迎船忆旧时。\n庐下夜来霜屦冷，袜材持送懒残师。",
        "dynasty": "宋",
        "collection_info": null
    },
    {
        "uuid": "63c92a2850082ed6c9f79b9effd45d00",
        "title": "次韵李竹坞怀古",
        "author": "马廷鸾",
        "content": "宝箓炎图未百年，神徂圣伏一凄然。\n征先生起淹中礼，与老人期圯上编。\n柯烂不惊人换世，瓢空独乐士希贤。\n昌黎愤世犹稽古，难拗何妨只自鞭。",
        "dynasty": "宋",
        "collection_info": null
    },
    {
        "uuid": "d79301db2422a8f3c45b2725985d746d",
        "title": "拜屺瞻墓有感",
        "author": "马廷鸾",
        "content": "我走金塘十五年，新年六十意凄然。\n扶藜策蹇趋庐下，洗盏将雏拜影前。\n蠹化不妨松饮露，凤栖犹拟柏参天。\n微吟缓步沧江晚，一抹青山落照边。",
        "dynasty": "宋",
        "collection_info": null
    },
    {
        "uuid": "5010c6aab93793be2f8900b4bd6f549c",
        "title": "我辈小年端午给假蒲酒奉亲之外日游村田间致足乐也今老矣竹坞老友近馆授徒逢此小熟奉一酌道旧且有感于并汾旧事云",
        "author": "马廷鸾",
        "content": "香罗细葛端阳节，绛帐青衿少小时。\n曩以弹丸俘晋孽，今于筒黍弔湘纍。\n千年感旧慵开卷，一酌销忧强把巵。\n蒲酒少年供母后，村南村北恣游嬉。",
        "dynasty": "宋",
        "collection_info": null
    },
    {
        "uuid": "8ce1d3700c2f8bee56570c6c318cb29d",
        "title": "五月二十夜记梦",
        "author": "马廷鸾",
        "content": "生来不作浮名计，老去翻惊幽梦奇。\n宫黍不知哀九庙，廷麻犹听拜三师。\n睡昏拟草榻前疏，寤辟疑催牖下期。\n更把在前荣路看，痴翁说梦尽添痴。",
        "dynasty": "宋",
        "collection_info": null
    },
    {
        "uuid": "54ff13a188989d3c0ab9e910194ff25c",
        "title": "德寿宫古松太上爱之尝持御香酾酒祠土神以祈屏蟊贼云时绍兴壬午思陵馘亮之岁也于今百二十年矣仆生六十年后而十月八日又思陵上仙之晨感而有赋  其一",
        "author": "马廷鸾",
        "content": "六龙亲御奠神州，甲子如今甫再周。\n百世尚瞻虞帝祀，五传遽抱杞天忧。\n臣民莫废瓜华敬，今古长悲禾黍秋。\n叹息余生孤露甚，门弧弓棘总成愁。",
        "dynasty": "宋",
        "collection_info": null
    },
    {
        "uuid": "94155c92103764019548ec332b02b569",
        "title": "德寿宫古松太上爱之尝持御香酾酒祠土神以祈屏蟊贼云时绍兴壬午思陵馘亮之岁也于今百二十年矣仆生六十年后而十月八日又思陵上仙之晨感而有赋  其二",
        "author": "马廷鸾",
        "content": "南来天马总辛勤，内禅经今历再壬。\n復汉赤符还旧宇，法尧黄屋本非心。\n思成门外衣冠尽，德寿宫前茨棘深。\n嘆息余生孤露甚，匪莪彼黍涕淋淫。",
        "dynasty": "宋",
        "collection_info": null
    },
    {
        "uuid": "dce4a2388021d73e58cb6fd55b5f9f81",
        "title": "又题德寿宫古松",
        "author": "马廷鸾",
        "content": "千岁堂堂十八公，雨膏露沐贮清风。\n龙吟高啸长身客，蠹化低摧秃鬓翁。\n谁谓蚍蜉能撼树，不堪蟊贼欲蟠空。\n御香洒酒荒荆棘，肠断孤臣泣寿宫。",
        "dynasty": "宋",
        "collection_info": null
    },
    {
        "uuid": "22a34e02ca14badcca4fbf5eecb167d1",
        "title": "与三儿涉穰田渡车中读朱忠靖中兴事实有感",
        "author": "马廷鸾",
        "content": "骚情长爱重阳近，客路归迟夕照西。\n举目山河秋寂寂，满城风雨晚凄凄。\n老思旧隠盟鸥社，寒涉深流信马蹄。\n凭轼试看炎绍录，空嗟语石与天齐。",
        "dynasty": "宋",
        "collection_info": null
    },
    {
        "uuid": "0a5453ef59ab8ccdf8a11b9bc4bcef83",
        "title": "十月八日有感",
        "author": "马廷鸾",
        "content": "日来天马愤挥戈，直为当年斧画河。\n万炬莲灯照鲸海，一杯麦饭渡滹沱。\n思陵录上哀荣极，德寿宫前耆旧多。\n忍把原碑参叶记，江头石刻懒摩挲。",
        "dynasty": "宋",
        "collection_info": null
    },
    {
        "uuid": "58d06b04a409f915314917b556d747ea",
        "title": "十月二十日有感",
        "author": "马廷鸾",
        "content": "精一危微尚赘辞，只须三语好为之。\n风清月白此良夜，雪暗云昏彼一时。\n玉斧照廊开嗣圣，金縢纳册付宫姬。\n思成门外荒荆棘，惆怅何人失令规。",
        "dynasty": "宋",
        "collection_info": null
    },
    {
        "uuid": "094e69ef9b7df196acf914feeefc9769",
        "title": "外孙朱饶归吴兴",
        "author": "马廷鸾",
        "content": "出门一别行千里，闭户归休读五车。\n天路尘冥车服骥，世科墨湿字翻鸦。\n绣綳尚忆春晖报，云舍无令暮霭遮。\n晚岁饰巾吾待尽，高空摩翮汝横斜。",
        "dynasty": "宋",
        "collection_info": null
    },
    {
        "uuid": "307a5053324d9fa6fb9b0b6ca6204720",
        "title": "七夕雨中饮客",
        "author": "马廷鸾",
        "content": "羁怀病思不禁秋，又报西风大火流。\n梧叶未凋高树翠，薇花不厌小山幽。\n燕鸿来往书生老，禾黍高低故国愁。\n志士悲秋宁復尔，楼头罇酒漫销忧。",
        "dynasty": "宋",
        "collection_info": null
    },
    {
        "uuid": "585127703d165cb53f4350d7fd2f9344",
        "title": "十月二十日感旧",
        "author": "马廷鸾",
        "content": "九衢灯火闹嘈嘈，斗柄低昂列宿高。\n漏箭声沉金锁彻，纱笼影避贵官豪。\n乌号望帝穷霄壤，鱼烂遗民沸海涛。\n三百五年风雪夕，孤臣白首卧林皋。",
        "dynasty": "宋",
        "collection_info": null
    },
    {
        "uuid": "ae379c19538fa51977cd65857b432d0f",
        "title": "正月四日",
        "author": "马廷鸾",
        "content": "皇厌纷拏五季余，万兵朝遣暮还都。\n虎头预卜清明旦，鳌足重开混一区。\n天下归仁吾有道，日中为市尔无虞。\n孤臣白首怀佳节，奠桂焚兰泪与俱。",
        "dynasty": "宋",
        "collection_info": null
    },
    {
        "uuid": "25c8a4c001b99c28608d63c89b194481",
        "title": "次张龙山韵反骚",
        "author": "马廷鸾",
        "content": "雪柏霜松自有神，衝风槁叶故难禁。\n云间已閟贞元曲，岁晚谁闻正始音。\n天地有穷归幻化，圣贤无命亦山林。\n愁来又把离骚读，长夜悠悠慷慨吟。",
        "dynasty": "宋",
        "collection_info": null
    },
    {
        "uuid": "d5ee357464840d015e79ad2d6836890d",
        "title": "冬至",
        "author": "马廷鸾",
        "content": "山寒律管又飞灰，万壑松风冬起雷。\n风景不殊云黯淡，雪霜初霁日徘徊。\n无人献袜抛尘屦，有客传觞酦冻醅。\n天地不教阳德尽，韦编曾叩伏羲来。",
        "dynasty": "宋",
        "collection_info": null
    },
    {
        "uuid": "334006201092f7e32bf32ede5328feaa",
        "title": "次韵洁堂别岁",
        "author": "马廷鸾",
        "content": "月底南枝插屋椽，无人共赏祇凋年。\n我惭王氏青毡旧，君效坡翁白鹤迁。\n小隠未荒存菊径，独清难涴出山泉。\n归时好待春江涨，稳泛轻舟一叶莲。",
        "dynasty": "宋",
        "collection_info": null
    },
    {
        "uuid": "84421ad7ff80e096523cd8b09d807b73",
        "title": "用洁堂韵赠徐清溪祷雨",
        "author": "马廷鸾",
        "content": "怒起乖龙变蛰雷，神翁此手更神哉。\n老天于物何尝病，旧雨如人自不来。\n彼稷之苗余滞穗，我行其野绝纤埃。\n方平狡狯犹余事，聊慰饥农取大咍。",
        "dynasty": "宋",
        "collection_info": null
    },
    {
        "uuid": "7b0419d3093f4e36ddb672ec7d102cb6",
        "title": "得熊静程主簿书且诲以二父庚甲用旧韵奉寄",
        "author": "马廷鸾",
        "content": "负米无亲不忍尝，谁为故老在邻墙。\n百年宁復知耆旧，六甲犹能记岁阳。\n襟佩书生联讲席，鼓旗骚将角名场。\n斯文未敢荒先绪，白首遗孤腼最良。",
        "dynasty": "宋",
        "collection_info": null
    },
    {
        "uuid": "44f337457be78ef6c6918cd98421a7e9",
        "title": "苦雨",
        "author": "马廷鸾",
        "content": "倦夜抛书病不禁，投床无寐雨涔涔。\n长潸旧国山河泪，细滴孤臣禾黍心。\n狂象蹋池喧泞淖，饥鸦谋稻怆淋淫。\n天公老手须斟酌，次第龙分正望霖。",
        "dynasty": "宋",
        "collection_info": null
    },
    {
        "uuid": "6d5f92696cf90934afa7ad18f8d16634",
        "title": "谢毛子文见寿",
        "author": "马廷鸾",
        "content": "编排老朽我为魁，绿鬓朱颜可得迴。\n周雅辍吟悲顾復，楚骚长嘆诵恢台。\n鸿飞灭没孤身在，燕逐炎凉几客来。\n苜宿黎祁汤餠供，一浇眊矂强持杯。",
        "dynasty": "宋",
        "collection_info": null
    },
    {
        "uuid": "e83f7a12a945a5a5c1f0560bcd564ec0",
        "title": "次韵朱婿实甫见寿",
        "author": "马廷鸾",
        "content": "南华参透解天刑，夜夜心香祷玉衡。\n紫盖十年违帝阙，青山九琐梦云京。\n缁郎宁忍忘天佑，白傅空令羡普明。\n人以寿欢臣以戚，孤怀借酒为浇平。",
        "dynasty": "宋",
        "collection_info": null
    },
    {
        "uuid": "25e479d86a747cef7278f009b6960bce",
        "title": "观鱼车渡溪",
        "author": "马廷鸾",
        "content": "如带溪流拍两崖，投泥贾客竞喧豗。\n隻轮自力掀诸淖，断岸先登陟彼嵬。\n江水斗升宁汝活，岸旁车马为渠来。\n老夫自取鲸鲵戮，掩鼻沙丘未足哀。",
        "dynasty": "宋",
        "collection_info": null
    },
    {
        "uuid": "b2d839a6e7719809f5ad771b3755d7df",
        "title": "北平家传成  其一",
        "author": "马廷鸾",
        "content": "三百年间事屡危，降之人杰岂中衰。\n巍巍祖烈将千岁，赫赫元功彼一时。\n起义堂碑云汉丽，凌烟阁像日星垂。\n藏山自纂前朝史，付与云礽百代知。",
        "dynasty": "宋",
        "collection_info": null
    },
    {
        "uuid": "ff341f198fd3bfa36e2b34aecc30949a",
        "title": "北平家传成  其二",
        "author": "马廷鸾",
        "content": "选将初年起范阳，和戎晚节误平凉。\n大功宜受春秋责，盛毁何能日月伤。\n文士谈兵多谬误，兰台作史漫裁量。\n折衷自有成书在，公论从知千岁长。",
        "dynasty": "宋",
        "collection_info": null
    },
    {
        "uuid": "5fbe72865632eafa4a14f019ecca493c",
        "title": "北平家传成  其三",
        "author": "马廷鸾",
        "content": "彼美人兮无古今，挑灯勘史夜沉沉。\n昌唐无復浯溪颂，哀郢常多楚泽吟。\n麟获自伤王迹息，鹃啼谁念帝魂深。\n祇今莫唱贞元曲，但忆曾闻正始音。",
        "dynasty": "宋",
        "collection_info": null
    },
    {
        "uuid": "9a88e66c2d1f239e479f23f20e38e896",
        "title": "饯朱婿",
        "author": "马廷鸾",
        "content": "哀郢那能拾穗歌，卧陶谁復杖藜过。\n白头老我已如此，青眼看君余几何。\n风雨夜吟蛩满砌，云山寒影鴈横坡。\n暮年亲友临分苦，小酌村醪借脸酡。",
        "dynasty": "宋",
        "collection_info": null
    },
    {
        "uuid": "0ebb6d8df59ab0cf4ff15c2866e81fd0",
        "title": "屺瞻拜墓  其一",
        "author": "马廷鸾",
        "content": "老诵劬劳易感伤，一年一度拜金塘。\n食莲正忆慈颜远，毁璧新增苦泪滂。\n松蠹穹林成秃帚，草荒高冢蔽幽篁。\n山哀浦思愁余极，阵阵溪风叶叶黄。",
        "dynasty": "宋",
        "collection_info": null
    },
    {
        "uuid": "83183f44ce9370a48ebf6a13a36e5cef",
        "title": "屺瞻拜墓  其二",
        "author": "马廷鸾",
        "content": "假汝稀年只八年，争教老境不凄然。\n青山慈母已黄壤，绿鬓中男余白颠。\n天外羣鸿随灭没，云间孤鹤自蹁跹。\n共携斗酒浇坟土，衰泪何由滴到泉。",
        "dynasty": "宋",
        "collection_info": null
    },
    {
        "uuid": "95a7926d5962361f13e9383d422d17d9",
        "title": "宿屺瞻夜赋  其一",
        "author": "马廷鸾",
        "content": "咿轧篮舆度晓岑，抚今怀昔泪淋淫。\n蓼莪老去仍追诵，常棣新来又废吟。\n有恨台瓜随蔓尽，无情涧藻与波沉。\n僧窗月苦夜无寐，莫咏儿寒动母心。",
        "dynasty": "宋",
        "collection_info": null
    },
    {
        "uuid": "4c2afcd0f187ba4d4d7ae17490b7f095",
        "title": "宿屺瞻夜赋  其二",
        "author": "马廷鸾",
        "content": "六十年前我已孤，婴儿抱母泣呱呱。\n昊天罔极幽明隔，良月就盈今昔殊。\n云塞断行悲独鴈，风林反哺感羣乌。\n澄江只似洹河水，一碧寒泓照白鬚。",
        "dynasty": "宋",
        "collection_info": null
    },
    {
        "uuid": "d2e9063f288d4078d85a1d6a4606df2f",
        "title": "过屺瞻墓",
        "author": "马廷鸾",
        "content": "白髮苍颜六十三，年年拜母忆中男。\n云归别岫山呈碧，江抱寒汀水染蓝。\n草报春晖天罔极，树随人老我何堪。\n荐余煮茗清泉供，泪泫余潸酒不酣。",
        "dynasty": "宋",
        "collection_info": null
    },
    {
        "uuid": "c2982ba489638f99a00504605356cc78",
        "title": "屺瞻道中  其一",
        "author": "马廷鸾",
        "content": "蓐食需明出远村，笋舆咿轧睡昏昏。\n禾麻丰岁云连亩，风露高秋水落痕。\n清晓跨鞍儿从父，当年戏綵母怜孙。\n白头老病松楸隔，一望云飞一断魂。",
        "dynasty": "宋",
        "collection_info": null
    },
    {
        "uuid": "fb766730358a1bde5ca5a5d9c70d2667",
        "title": "屺瞻道中  其二",
        "author": "马廷鸾",
        "content": "波粼粼处浅溪沙，渔屋低迷舴艋家。\n地老天荒原野静，江空岁晚水云赊。\n淤泥日课黄金粟，清泚时吹白浪花。\n漫喜时丰阡陌裏，豚蹄行矣祝污邪。",
        "dynasty": "宋",
        "collection_info": null
    },
    {
        "uuid": "1183e1bce1a838105d0cabc27b88bca5",
        "title": "山中对紫薇花书感",
        "author": "马廷鸾",
        "content": "轻盈插向胆瓶中，看到山林禁籞同。\n阁下天葩秋月黯，楼头奎画晓云空。\n高攀玉树扶斑白，静扫苍苔拾堕红。\n三十年前天上梦，老来无泪洒西风。",
        "dynasty": "宋",
        "collection_info": null
    },
    {
        "uuid": "1502b335f7fc4c4789a2a29ed30b1352",
        "title": "次许表兄韵",
        "author": "马廷鸾",
        "content": "物换星移一慨然，天荒地老断鳌前。\n岂无志士王官谷，亦有飞仙太华巅。\n我若加三逢本命，君今过一渐稀年。\n两人中表俱头白，蜀馈纔堪几幅笺。",
        "dynasty": "宋",
        "collection_info": null
    },
    {
        "uuid": "ac6505e299e15160b028cfde8eb32ab6",
        "title": "次龙山韵  其一",
        "author": "马廷鸾",
        "content": "新来霄汉冥鸿客，旧日风云振鹭行。\n脱下戏衫优便散，惊回客枕梦何长。\n莫将吴蜀分岐路，政把干坤作醉乡。\n惟有葵倾心不死，清魂几到殿中央。",
        "dynasty": "宋",
        "collection_info": null
    },
    {
        "uuid": "3d8edc41761b0869390596374f97d9f0",
        "title": "次龙山韵  其二",
        "author": "马廷鸾",
        "content": "窗间莫问唤祁嘉，望断宗周黍稷华。\n斗帐高眠聊避客，深衣暂到漫为家。\n我怀荒草同元亮，君悼空絃谢伯牙。\n老矣悲欢总无奈，仙书频读览荒遐。",
        "dynasty": "宋",
        "collection_info": null
    },
    {
        "uuid": "cafc1cf1bec3a2eccf565fbc6f60eebd",
        "title": "拜饯修史大着吏部使浙西",
        "author": "马廷鸾",
        "content": "高怀岂必薄昆崙，揽辔登车意自欣。\n周太史官惭着我，汉常平使喜推君。\n庐山向已高千仞，野水从今宽一分。\n□□鹔鹴裘供□，□□□□更纷纷。",
        "dynasty": "宋",
        "collection_info": null
    },
    {
        "uuid": "302cf3eb8f6745c5d6c8092a94bd02f3",
        "title": "仰和皇太子殿下明禋庆成诗韵  其一",
        "author": "马廷鸾",
        "content": "圣主精禋格，明廷对月深。\n元良赞宸极，盛德享天心。",
        "dynasty": "宋",
        "collection_info": null
    },
    {
        "uuid": "2f2ecb1891eb1b4f6e64b2fc8880b980",
        "title": "仰和皇太子殿下明禋庆成诗韵  其二",
        "author": "马廷鸾",
        "content": "夕宿犹疎雨，昕朝覩大明。\n重光符景贶，熈事庆昇平。",
        "dynasty": "宋",
        "collection_info": null
    },
    {
        "uuid": "c56370c8915f85ada49c82e20583ad8f",
        "title": "仰和皇太子殿下明禋庆成诗韵  其三",
        "author": "马廷鸾",
        "content": "鸣銮回紫禁，步玉捧宸旒。\n肆眚遵虞典，欢传十二州。",
        "dynasty": "宋",
        "collection_info": null
    },
    {
        "uuid": "c282a72a0ed1347f79d4f8810d0fbf1c",
        "title": "用清秋鹤髮翁韵赋小书招洁堂  其一",
        "author": "马廷鸾",
        "content": "幽居抱孤明，怀古思旧京。\n渴望宝连山，老桂不胜清。",
        "dynasty": "宋",
        "collection_info": null
    },
    {
        "uuid": "ce5bf9e40e54f7ca7cb85aac2550b791",
        "title": "用清秋鹤髮翁韵赋小书招洁堂  其二",
        "author": "马廷鸾",
        "content": "月照窗炯炯，虫鸣室幽幽。\n策杖柴门晓，菰蒲半沼秋。",
        "dynasty": "宋",
        "collection_info": null
    },
    {
        "uuid": "3a022c022938b310ba81cd40c5d450a1",
        "title": "用清秋鹤髮翁韵赋小书招洁堂  其三",
        "author": "马廷鸾",
        "content": "火中寒暑退，造物其犹醵。\n老身不茧蚕，清夜独警鹤。",
        "dynasty": "宋",
        "collection_info": null
    },
    {
        "uuid": "efe7f41dee9eb0d4dd29e16dca3a572e",
        "title": "用清秋鹤髮翁韵赋小书招洁堂  其四",
        "author": "马廷鸾",
        "content": "老蟾明孤心，凉飈苏病骨。\n保此中夜存，微阳有毫髮。",
        "dynasty": "宋",
        "collection_info": null
    },
    {
        "uuid": "2316fb02f46185259105d714964dbd0f",
        "title": "用清秋鹤髮翁韵赋小书招洁堂  其五",
        "author": "马廷鸾",
        "content": "庭草无言绿，林花取意红。\n因之酌茅柴，招唤西邻翁。",
        "dynasty": "宋",
        "collection_info": null
    },
    {
        "uuid": "4511da59b0d183075ae6341f48ca9aa2",
        "title": "和洁堂见寿十章  其一",
        "author": "马廷鸾",
        "content": "老色上尺宅，灵气亏三田。\n怀我长房翁，授汝鸡犬仙。",
        "dynasty": "宋",
        "collection_info": null
    },
    {
        "uuid": "23c5007dd5f353585538f4a67db4a125",
        "title": "和洁堂见寿十章  其二",
        "author": "马廷鸾",
        "content": "早知无廊庙，胡不素丘园。\n挥手谢世氛，保此中夜存。",
        "dynasty": "宋",
        "collection_info": null
    },
    {
        "uuid": "7361fdf8f8a35f5f7623567925c893ab",
        "title": "和洁堂见寿十章  其三",
        "author": "马廷鸾",
        "content": "我生嘉定间，宝运稽炎隆。\n当时贡珍祥，今日泣麟穷。",
        "dynasty": "宋",
        "collection_info": null
    },
    {
        "uuid": "3e27723802200b173e60510a0cc0f5f1",
        "title": "和洁堂见寿十章  其四",
        "author": "马廷鸾",
        "content": "风雨倾燕巢，波涛涨鲸海。\n茅檐得此生，其谁为尔宰。",
        "dynasty": "宋",
        "collection_info": null
    },
    {
        "uuid": "ad5003ed24b8657071ee266af14d17f6",
        "title": "和洁堂见寿十章  其五",
        "author": "马廷鸾",
        "content": "大冬严寒至，病骨裹粗纩。\n羸然祝鸡翁，不识山中相。",
        "dynasty": "宋",
        "collection_info": null
    },
    {
        "uuid": "8ffb087e7e2fc445e2d64c6a3a0317ce",
        "title": "和洁堂见寿十章  其六",
        "author": "马廷鸾",
        "content": "琅琅金薤篇，慰此暮年癯。\n诵我征咎赋，夸君摘句图。",
        "dynasty": "宋",
        "collection_info": null
    },
    {
        "uuid": "7d323194ba554fc5174c636a27ee38c4",
        "title": "和洁堂见寿十章  其七",
        "author": "马廷鸾",
        "content": "丧乱属何辜，吁吁者谁子。\n生来乏远猷，死去忧良史。",
        "dynasty": "宋",
        "collection_info": null
    },
    {
        "uuid": "3fd1dd9b31f28be0abf2b9c48af170ad",
        "title": "和洁堂见寿十章  其八",
        "author": "马廷鸾",
        "content": "道义挹亲仁，诗书仰邻富。\n翠蓬羞排门，骊珠惊满袖。",
        "dynasty": "宋",
        "collection_info": null
    },
    {
        "uuid": "911889de005703a996cd802a027e5356",
        "title": "和洁堂见寿十章  其九",
        "author": "马廷鸾",
        "content": "山哀兮浦思，月诸兮日居。\n伊谁百岁期，迟汝十年书。",
        "dynasty": "宋",
        "collection_info": null
    },
    {
        "uuid": "80e5c8d3a01fb41bb08b95746a47b497",
        "title": "和洁堂见寿十章  其一○",
        "author": "马廷鸾",
        "content": "祝公千龄寿，小我五月生。\n如何山林槁，得并江汉英。",
        "dynasty": "宋",
        "collection_info": null
    },
    {
        "uuid": "5a3b29f69aa31909e825077048787378",
        "title": "赠张君  其一",
        "author": "马廷鸾",
        "content": "世间草隶是云礽，汲冢深埋唤不譍。\n五百年间徐骑省，一千年后李阳冰。",
        "dynasty": "宋",
        "collection_info": null
    },
    {
        "uuid": "d4fb57548da7f098a8dd1ecf343327fb",
        "title": "赠张君  其二",
        "author": "马廷鸾",
        "content": "人生识字忧患始，底用区区更出奇。\n我欲扫空閒笔墨，只凭老腕把锄犂。",
        "dynasty": "宋",
        "collection_info": null
    },
    {
        "uuid": "3b56314b89d26fa19e8838cdf7e21d02",
        "title": "赠铁面王说易",
        "author": "马廷鸾",
        "content": "春风吹袂过溪塘，有客来称铁面郎。\n今代贵人甘软媚，可能骯脏倚门墙。",
        "dynasty": "宋",
        "collection_info": null
    },
    {
        "uuid": "de9c36f332a4158a26b318c515494b67",
        "title": "京邸漫题",
        "author": "马廷鸾",
        "content": "不遑将母兄嗟弟，无以为家尔与余。\n独坐小楼风雨急，江南岁晚鴈何如。",
        "dynasty": "宋",
        "collection_info": null
    },
    {
        "uuid": "855d755a31bdad3cdd2e260d2c4f1ccf",
        "title": "赠彭瀛洲",
        "author": "马廷鸾",
        "content": "芸香茗供尽清流，十八仙人忆旧游。\n要是山中好风月，年来无梦到瀛洲。",
        "dynasty": "宋",
        "collection_info": null
    },
    {
        "uuid": "bd1dad67d59c63f672e39fc91c356d56",
        "title": "示程介夫  其一",
        "author": "马廷鸾",
        "content": "流年何必共君参，九琐青山老一庵。\n试检乐天诗集看，明年半百又加三。",
        "dynasty": "宋",
        "collection_info": null
    },
    {
        "uuid": "e8de03cae0820aacb4a9e8d4ee83c1d6",
        "title": "示程介夫  其二",
        "author": "马廷鸾",
        "content": "羊肠路险百千转，云梦胸吞八九宽。\n豆饭芋羹纔足欲，水边林下即心安。",
        "dynasty": "宋",
        "collection_info": null
    },
    {
        "uuid": "00b869734c289b1c4532bf6c2ce54f20",
        "title": "迎新仓守曾悦心道间偶赋",
        "author": "马廷鸾",
        "content": "黄旗红帜走踆踆，晓出闉阇奔迓新。\n车盖如云骑如水，山头牛背有閒人。",
        "dynasty": "宋",
        "collection_info": null
    },
    {
        "uuid": "4c301c23132fbed3453e401bf8c6163c",
        "title": "题张氏勤有堂",
        "author": "马廷鸾",
        "content": "世间义理尽无涯，桃李春风总一家。\n最恨一般浮浅学，卖花担上漫看花。",
        "dynasty": "宋",
        "collection_info": null
    },
    {
        "uuid": "26415f6edc119ecc7ffa4678fe97d374",
        "title": "题赵君画竹",
        "author": "马廷鸾",
        "content": "霜竿操尚特幽奇，直节端如正士姿。\n高拂九霄无曲处，古来惟有老天知。",
        "dynasty": "宋",
        "collection_info": null
    },
    {
        "uuid": "daca81e038006259f69596a08f34f318",
        "title": "八月十四日记梦",
        "author": "马廷鸾",
        "content": "断鳌立极有前闻，鬰鬰昌陵颠蘗春。\n起自郇瑕形自着，晓然入梦匪纷纭。",
        "dynasty": "宋",
        "collection_info": null
    },
    {
        "uuid": "c02de4a59584c02a6d4520aa6d77bf12",
        "title": "弔柴道士",
        "author": "马廷鸾",
        "content": "老子犹龙不可亲，庄周与蝶孰为真。\n补还石鼎吟边句，飞作临皋梦裏人。",
        "dynasty": "宋",
        "collection_info": null
    },
    {
        "uuid": "24896f6e5ef1363e542ae28de43fdd38",
        "title": "谢洁斋惠炉瓶  其一",
        "author": "马廷鸾",
        "content": "午梦惊残拨白灰，满盘云篆拂轻煤。\n金猊对舞轮囷吐，曾挹天香鼻观来。",
        "dynasty": "宋",
        "collection_info": null
    },
    {
        "uuid": "d67d642ef973f61fd126d0df52246591",
        "title": "谢洁斋惠炉瓶  其二",
        "author": "马廷鸾",
        "content": "宴坐浑如槁木枝，垆烟瓶蕊小窗宜。\n书慵捲起閒今古，回向心源不动时。",
        "dynasty": "宋",
        "collection_info": null
    },
    {
        "uuid": "922b2646c401bb9e1c9b35c39ee01b29",
        "title": "带湖春树先和公手植也感而有赋  其一",
        "author": "马廷鸾",
        "content": "暗香疎影久凄迷，咫尺塘边丈尺泥。\n培植莫教阳德尽，看花踏雪过前堤。",
        "dynasty": "宋",
        "collection_info": null
    },
    {
        "uuid": "4d8bbc45b46e4adea1ce0004de77f6fb",
        "title": "带湖春树先和公手植也感而有赋  其二",
        "author": "马廷鸾",
        "content": "老树今踰七十霜，冰魂玉骨自孤芳。\n大家扶起摧残后，此是吾家召伯棠。",
        "dynasty": "宋",
        "collection_info": null
    },
    {
        "uuid": "3601bbb431279d75b91649f9e0e25317",
        "title": "感二李",
        "author": "马廷鸾",
        "content": "渡海归来一炷香，八斋早欲卧僧房。\n平泉免向崖州死，博得生前万口羊。",
        "dynasty": "宋",
        "collection_info": null
    },
    {
        "uuid": "b61e07d79bf5750334fe660747ad24ee",
        "title": "山中梅花  其一",
        "author": "马廷鸾",
        "content": "欲为山严作好歌，旧时挟册向山阿。\n我无缝雾裁云句，奈此层梯苏磴何。",
        "dynasty": "宋",
        "collection_info": null
    },
    {
        "uuid": "35c6f8138c3659de75e8773c3ca3a1df",
        "title": "山中梅花  其二",
        "author": "马廷鸾",
        "content": "霜崖雪壁花千树，玉骨冰魂月一痕。\n芳洁不为尘土涴，琼英跕跕堕云根。",
        "dynasty": "宋",
        "collection_info": null
    },
    {
        "uuid": "1197f6c70ae76ad8a8e795f3a72fc854",
        "title": "洁堂惠菜餠次韵",
        "author": "马廷鸾",
        "content": "落花寒食漫从容，野摘堪供菜肚翁。\n一笑琅玕青满腹，红绫还忆旧家风。",
        "dynasty": "宋",
        "collection_info": null
    },
    {
        "uuid": "a7355a47c6388081847d7f628d5b08f8",
        "title": "纪梦",
        "author": "马廷鸾",
        "content": "白日青天一鉅儒，清宵入梦忽蘧蘧。\n觉来猛省戊申疏，曾说中原乱易除。",
        "dynasty": "宋",
        "collection_info": null
    },
    {
        "uuid": "5a168474cf0288aa99e6646371e47061",
        "title": "赠刊字汤生德清",
        "author": "马廷鸾",
        "content": "岐阳雨渍镌功石，浯水苔昏颂德碑。\n渺渺昊天须有定，烦君椎凿待明时。",
        "dynasty": "宋",
        "collection_info": null
    },
    {
        "uuid": "0f69fcfa6113d4094d4296b59f5ff441",
        "title": "感时寄钟信甫",
        "author": "马廷鸾",
        "content": "子陵滩下立多时，鸥鹭悠悠自识机。\n春事都来无半月，一声鶗鴂劝人归。",
        "dynasty": "宋",
        "collection_info": null
    },
    {
        "uuid": "48dd0f417cc2a230c09b4407bb21d48e",
        "title": "纪梦",
        "author": "马廷鸾",
        "content": "夜梦嬉游到古陂，翻菱剥芡不知归。\n野田没膝泥三尺，拔足污渠自一奇。",
        "dynasty": "宋",
        "collection_info": null
    },
    {
        "uuid": "6fd9ef46f6dbb879d98b7174f123cfa2",
        "title": "十月二十六日有感",
        "author": "马廷鸾",
        "content": "宾空后甲再经壬，香断金炉已七春。\n四十一年民父母，谁知今日帝乘云。",
        "dynasty": "宋",
        "collection_info": null
    },
    {
        "uuid": "44f062afd143074074fa51fc3113871a",
        "title": "求菖蒲于李叔翔",
        "author": "马廷鸾",
        "content": "风饕雪虐岁峥嵘，寸草寒窗独宁馨。\n长恐出山泉水浊，尘埃到汝失青青。",
        "dynasty": "宋",
        "collection_info": null
    },
    {
        "uuid": "217daec6b1c87b2cf7ce5b2c76c8c769",
        "title": "和许膝啸韵  其一",
        "author": "马廷鸾",
        "content": "尘满莱衣泪点斑，春风桃李见应难。\n奎文忽到茅檐下，忍作当年义檄看。",
        "dynasty": "宋",
        "collection_info": null
    },
    {
        "uuid": "6703c7e010cb75e891ba61cc1416e8a6",
        "title": "和许膝啸韵  其二",
        "author": "马廷鸾",
        "content": "前年儤直玉堂庐，下直归迟母倚闾。\n早识千钟误三釜，斑衣换得锦衣无。",
        "dynasty": "宋",
        "collection_info": null
    },
    {
        "uuid": "4e3ffadda1f4fc55339401518d4b9f42",
        "title": "陈菊圃参政寄诗千里外託兴于秋燕春花以示玩芳病叟叟病不能吟强和四章前二章借来意以自伤后二章述愚怀以志感  其一",
        "author": "马廷鸾",
        "content": "风雨危巢萎百花，坐看百鸟竞衔茶。\n斜阳对语归飞处，底是乌衣王谢家。",
        "dynasty": "宋",
        "collection_info": null
    },
    {
        "uuid": "533ac84c02f0e35952f6e7da769584eb",
        "title": "陈菊圃参政寄诗千里外託兴于秋燕春花以示玩芳病叟叟病不能吟强和四章前二章借来意以自伤后二章述愚怀以志感  其二",
        "author": "马廷鸾",
        "content": "桃李盘中天地宽，误渠鼎实为才悭。\n苔荒草没浑无耻，犹自青黄烟雨间。",
        "dynasty": "宋",
        "collection_info": null
    },
    {
        "uuid": "0cd6ce22fe122a355b9d035ce695be5e",
        "title": "陈菊圃参政寄诗千里外託兴于秋燕春花以示玩芳病叟叟病不能吟强和四章前二章借来意以自伤后二章述愚怀以志感  其三",
        "author": "马廷鸾",
        "content": "冠峨獬豸服绯花，欲献甘芹谓苦茶。\n误尽灵乌报凶吉，终然爰止託谁家。",
        "dynasty": "宋",
        "collection_info": null
    },
    {
        "uuid": "5097a090a6ffba911c18fefd3fc3f1f2",
        "title": "陈菊圃参政寄诗千里外託兴于秋燕春花以示玩芳病叟叟病不能吟强和四章前二章借来意以自伤后二章述愚怀以志感  其四",
        "author": "马廷鸾",
        "content": "灿灿黄花老圃宽，秋芳不采岂云悭。\n江南九日闽千里，尚挹寒香纸墨间。",
        "dynasty": "宋",
        "collection_info": null
    },
    {
        "uuid": "fee7d38503b3940626ac62255e447fc4",
        "title": "寄题程氏菊庄  其一",
        "author": "马廷鸾",
        "content": "白贲黄中自不羣，冷霜凉露伴灵均。\n集芳尚恨椒兰变，何况夭桃俗李春。",
        "dynasty": "宋",
        "collection_info": null
    },
    {
        "uuid": "eba7ae7949ed8d83aad2f8dbfff3b358",
        "title": "寄题程氏菊庄  其二",
        "author": "马廷鸾",
        "content": "一觞浥露餐英美，八表同昏履运艰。\n芳节不随篱下老，悠悠嘉气眼中山。",
        "dynasty": "宋",
        "collection_info": null
    },
    {
        "uuid": "2f2ef5a74451590c6b69307eba6ed762",
        "title": "寄题程氏菊庄  其三",
        "author": "马廷鸾",
        "content": "一丘一壑图书府，三沐三熏烟雨中。\n只把空肠受寒绿，谁教腥腐涴清风。",
        "dynasty": "宋",
        "collection_info": null
    },
    {
        "uuid": "aba599bab02676f471fef6d62acce2d3",
        "title": "寄题程氏菊庄  其四",
        "author": "马廷鸾",
        "content": "最爱诚斋语绝佳，莫将清苦入妍华。\n淡香秋晚谁能道，犹是安阳昼锦家。",
        "dynasty": "宋",
        "collection_info": null
    },
    {
        "uuid": "57d37c36d4e5855b894550690bcf234e",
        "title": "寄题程氏菊庄  其五",
        "author": "马廷鸾",
        "content": "瓮裏酰鸡千岁灭，天边苍狗万重云。\n长生阅世凭何术，欲制颓龄藉此君。",
        "dynasty": "宋",
        "collection_info": null
    },
    {
        "uuid": "ecde382f4188de5f19558e6d5ce9278b",
        "title": "十月二十日  其一",
        "author": "马廷鸾",
        "content": "太乙宫前戎马乡，思成门外野蒿场。\n山中一瓣心香在，独遣孤臣病着床。",
        "dynasty": "宋",
        "collection_info": null
    },
    {
        "uuid": "a3c3ba0ea3ddadce8f2507d2a9aba54c",
        "title": "十月二十日  其二",
        "author": "马廷鸾",
        "content": "强提簪笏睇觚棱，再拜焚蕤泪雨零。\n千古陈桥仁圣事，不堪重勘旧编青。",
        "dynasty": "宋",
        "collection_info": null
    },
    {
        "uuid": "0e31d17335c5a31d89db975d13671969",
        "title": "读远游篇",
        "author": "马廷鸾",
        "content": "愁来高诵远游篇，度世长生岂可传。\n物变无穷身老矣，一鸡八谷又新年。",
        "dynasty": "宋",
        "collection_info": null
    },
    {
        "uuid": "991cac5188c55e5fd3801cb0e7f488c6",
        "title": "题杨妃唾壶图",
        "author": "马廷鸾",
        "content": "三郎好女思倾国，一霎沉酣四海奔。\n汉业巍巍英主事，内庭供奉孔家孙。\n汉武帝时执此物者侍中孔安国也，唐明皇时杨妃职之，汉唐之所以成败欤？然而宠任中书宦官，又自汉始。\n此话甚长，小子识之。",
        "dynasty": "宋",
        "collection_info": null
    },
    {
        "uuid": "d858face06726e5f0d06d5180067b5e2",
        "title": "九月十九夜纪梦",
        "author": "马廷鸾",
        "content": "堪嗟劫运永嘉末，忽梦清风干道初。\n二十年间閒处士，可能身世得同渠。",
        "dynasty": "宋",
        "collection_info": null
    },
    {
        "uuid": "f48cd6fe7d83ace838ab6369d406d320",
        "title": "十一月十二夜梦南冠旧友感泣有赋",
        "author": "马廷鸾",
        "content": "麦秀渐渐禾黍新，清宵梦断泣遗民。\n只怜肝脑输宗社，不负当年第一人。",
        "dynasty": "宋",
        "collection_info": null
    },
    {
        "uuid": "36f177d8739c29b9041a2ff3a6440ad4",
        "title": "题芳洲诗集  其一",
        "author": "马廷鸾",
        "content": "采采芹甘不自谋，慇懃直欲奉王羞。\n可怜斜日三千字，曾献当年十二旒。",
        "dynasty": "宋",
        "collection_info": null
    },
    {
        "uuid": "2826a7e8c126810cce9fc9182b8ab6be",
        "title": "题芳洲诗集  其二",
        "author": "马廷鸾",
        "content": "虎踞已知王气尽，鹃啼谁感帝魂哀。\n怪渠册后诗情苦，曾到留都丰镐来。",
        "dynasty": "宋",
        "collection_info": null
    },
    {
        "uuid": "9b72a6abb291cc382230c4b2ed7b7774",
        "title": "近闻在旧京卖缦笠子",
        "author": "马廷鸾",
        "content": "蚤岁葫芦依画本，暮年台笠养閒身。\n如今半幅誊麻纸，羞寄銮坡旧主人。",
        "dynasty": "宋",
        "collection_info": null
    },
    {
        "uuid": "175a62310b0253f6d92ba96f17fcce04",
        "title": "甲子初冬宿直玉堂凄风小雨次日即承先帝晏驾之变距今二十年矣大忌前一日孤臣独眠山庵景象正似当年挑灯危坐闻田家鼓笛之声凄其有感二首  其一",
        "author": "马廷鸾",
        "content": "无限都人哭鼎龙，年多泽久似仁宗。\n愁来一样黄昏雨，天上人间自不同。",
        "dynasty": "宋",
        "collection_info": null
    },
    {
        "uuid": "e79ca617d3aedd4c1dcb1546f84c4d30",
        "title": "甲子初冬宿直玉堂凄风小雨次日即承先帝晏驾之变距今二十年矣大忌前一日孤臣独眠山庵景象正似当年挑灯危坐闻田家鼓笛之声凄其有感二首  其二",
        "author": "马廷鸾",
        "content": "云黯天低结暝阴，孤灯对影夜沉沉。\n可怜一曲村田乐，犹是尧民击壤音。",
        "dynasty": "宋",
        "collection_info": null
    },
    {
        "uuid": "086d8452081a47ed6622e241546f02aa",
        "title": "挽许秋浦  其一",
        "author": "马廷鸾",
        "content": "纷纷顶板尽圈红，伯仲高鶱槐市风。\n一第不酬攀桂客，千年祇泣感麟翁。",
        "dynasty": "宋",
        "collection_info": null
    },
    {
        "uuid": "672276c4d0e1f61bc7d10d6fdda89646",
        "title": "挽许秋浦  其二",
        "author": "马廷鸾",
        "content": "苍颜白髮王官谷，绿幕黄帘六馆生。\n阅世旧嗟身偃蹇，怀人新有泪纵横。",
        "dynasty": "宋",
        "collection_info": null
    },
    {
        "uuid": "8dabb7c1b795563e0eca787679f0b89d",
        "title": "挽许秋浦  其三",
        "author": "马廷鸾",
        "content": "青门何在从瓜熟，玉水难忘对竹哦。\n政復安车裹轮好，情知老子不婆娑。",
        "dynasty": "宋",
        "collection_info": null
    },
    {
        "uuid": "3d86e6f059079bab251ffbf548df3891",
        "title": "挽许秋浦  其四",
        "author": "马廷鸾",
        "content": "歌骚读尽远游篇，淡日寒空引绋天。\n遶浦黄花秋易老，晚香留付子孙贤。",
        "dynasty": "宋",
        "collection_info": null
    },
    {
        "uuid": "d339d3a55403ece0a9c970495fb7fd15",
        "title": "挽张龙山  其一",
        "author": "马廷鸾",
        "content": "雄篇烂漫兔园册，挺翮扶摇鹏背风。\n揭日科名轻拾紫，粘天名姓捷圈红。",
        "dynasty": "宋",
        "collection_info": null
    },
    {
        "uuid": "c123a92902584409d8fa1258b746f1ba",
        "title": "挽张龙山  其二",
        "author": "马廷鸾",
        "content": "大雅林中集众英，三长正合入承明。\n汗青有日头无白，家传修来国史成。",
        "dynasty": "宋",
        "collection_info": null
    },
    {
        "uuid": "714e0aad4d8c4e97e5b7916d79da5756",
        "title": "挽张龙山  其三",
        "author": "马廷鸾",
        "content": "钦翘人物观奇士，芳润衣冠俨硕师。\n槐柳门前气成雾，清风茗碗只谈诗。",
        "dynasty": "宋",
        "collection_info": null
    },
    {
        "uuid": "f7c9e741a4e86534b13356a0c606d9b6",
        "title": "挽张龙山  其四",
        "author": "马廷鸾",
        "content": "诸公莫唱贞元曲，老子曾闻正始音。\n寂寞吴王堤上路，白杨花落昼多阴。",
        "dynasty": "宋",
        "collection_info": null
    },
    {
        "uuid": "bb5732d83b39c3352cc77068a91aa0ed",
        "title": "挽李小溪  其一",
        "author": "马廷鸾",
        "content": "人是西京长者孙，横秋一鹗早青云。\n假令折就天边桂，窦十郎家不足云。",
        "dynasty": "宋",
        "collection_info": null
    },
    {
        "uuid": "f67acfa6e3281e97ac2185c438ce6165",
        "title": "挽李小溪  其二",
        "author": "马廷鸾",
        "content": "三十年间借一瓻，鹄袍门外欠相携。\n降霜御史风棱恶，瞎眼春官日色迷。",
        "dynasty": "宋",
        "collection_info": null
    },
    {
        "uuid": "b5ebee98e9630349b0a947bb18179168",
        "title": "挽李小溪  其三",
        "author": "马廷鸾",
        "content": "鬰鬰南坡一聚尘，荒园野草不成春。\n家声久矣非前日，宅相居然亦古人。",
        "dynasty": "宋",
        "collection_info": null
    },
    {
        "uuid": "1eeeea521d942e367adb7b8448338581",
        "title": "挽李小溪  其四",
        "author": "马廷鸾",
        "content": "仙李由来公与侯，宋唐相望尽名流。\n金銮论事嗟无地，往遡天风记玉楼。",
        "dynasty": "宋",
        "collection_info": null
    },
    {
        "uuid": "c506a21a197028eabc46da5063428e07",
        "title": "题老学道院  其一",
        "author": "马廷鸾",
        "content": "天典民彜圣得知，斯文千岁以为期。\n试看涑水三雍赞，何必兰陵赋诡诗。",
        "dynasty": "宋",
        "collection_info": null
    },
    {
        "uuid": "1a430d790149d5b7bbdc7ba714068850",
        "title": "题老学道院  其二",
        "author": "马廷鸾",
        "content": "瓜烂东陵老废锄，野民八十尚躭书。\n窗风文字翻叶叶，抱膝长吟一拥炉。",
        "dynasty": "宋",
        "collection_info": null
    },
    {
        "uuid": "5603fce66c29701a6cfb218c7af0b029",
        "title": "题老学道院  其三",
        "author": "马廷鸾",
        "content": "白日临晨老可娱，平生有味太玄𤕠。\n莫将华皓嗤童习，更采玄文扁此庐。",
        "dynasty": "宋",
        "collection_info": null
    },
    {
        "uuid": "e7525b824d568b5a628efece352623bb",
        "title": "题老学道院  其四",
        "author": "马廷鸾",
        "content": "繁笔泉石两成痴，早学东家晚学西。\n章甫峨峨宁汝误，如今翻恨十年迟。",
        "dynasty": "宋",
        "collection_info": null
    },
    {
        "uuid": "eeafecf9d0ff742d132355414857c86e",
        "title": "益国赵公生祠",
        "author": "马廷鸾",
        "content": "康山之崇兮，公惠不穷兮。\n洎水之阳兮，公惠寖长兮。\n山浮清兮水涵晖，公有惠泽兮民有秉彜。\n坚珉深刻兮，来者永思。",
        "dynasty": "宋",
        "collection_info": null
    },
    {
        "uuid": "391ab1a11935e763fd94d9e59f0dd133",
        "title": "梓潼帝君祠",
        "author": "马廷鸾",
        "content": "梁山剑阁横岷嶓，梓潼七曲高嵯峨。\n真人初基斧画河，灵君受职山之阿。\n丹碧岌嶪龙虎呵，拄天功业石可磨。\n江流滔滔东逝波，灵之来兮自江沱。\n结屋兮奉祠，酿桂兮羞芝。\n神格思兮士曰时，跃渊兮天飞。\n冠若箕兮剑拄颐，长策用兮奇谋施，敌北遁兮灵西归。\n锦幡兮宝盖，导霓旌兮驾玉螭。\n吾言非夸兮，神之听之。",
        "dynasty": "宋",
        "collection_info": null
    },
    {
        "uuid": "ea5f08f5127e278cd4437bb95a837e08",
        "title": "饶娥庙祀神歌  其一",
        "author": "马廷鸾",
        "content": "日吉兮辰良，芳菲菲兮满堂。\n蕙殽烝兮兰藉，奠桂酒兮椒浆。\n灵连蜷兮既留，烂昭昭兮未央。\n驾飞龙兮于征，邅吾道兮乡之长城。\n波滔滔兮泪盈盈，望汾潭兮盘石横。\n僊滩兮扬灵，扬灵兮未极，隠思君兮太息。\n朝驰骛兮江之浔，夕弭节兮县西之侧，待娥不来兮使我心恻。",
        "dynasty": "宋",
        "collection_info": null
    },
    {
        "uuid": "4e94d94c12199057dc5334d980826655",
        "title": "饶娥庙祀神歌  其二",
        "author": "马廷鸾",
        "content": "我生之初尚无为，我生之后唐世衰。\n有父溺死兮谁者怜之，呼天与地兮涕涟洏。\n至险不测涛与风，至幽不仁鱼与龙，至孝不昧感即通。\n岂人之灵兮，不若厖之雄。\n惟天地之无穷兮，哀吾生之弱龄。\n往者吾不及兮，来者吾不获观其败与赢。\n愚公老矣山为平，精卫藐然海为倾。\n枕吾戈兮缚尔缨，猛志毅气妖氛澄。\n昊天克巩兮靡人弗胜，诵娥之烈兮摇我心旌。",
        "dynasty": "宋",
        "collection_info": null
    },
    {
        "uuid": "d4c8ac27e0f1773d15eedf5d0daedb8f",
        "title": "饶娥庙祀神歌  其三",
        "author": "马廷鸾",
        "content": "自我天覆，云之油油。\n大田多稼兮，屯膏是忧。\n雄虹朝隮兮，雌霓夕虬。\n触石兮通气，雷车兮电帜。\n雨甚至兮，神哉沛农。\n有成功兮，怀鸡黍之招邀。\n士未失职兮，冀鹏鲲之扶摇。\n锡之丰岁兮，俾尔余饶。\n报以修程兮，匪我宣骄。\n扬桴兮拊鼓，饯飈游兮远渚。\n欲少留此灵琐兮，日忽忽其将暮。\n祝娥之来下兮，慰我士民于终古。",
        "dynasty": "宋",
        "collection_info": null
    },
    {
        "uuid": "281aa29ba8c5c403d9e9ebebf45ea16f",
        "title": "赠山堂僧",
        "author": "马廷鸾",
        "content": "无生究竟是真源，浮世虚名可气吞。\n浄行要从圆处觅，好诗添向闷中喧。\n一心认我如如体，万事同渠莫莫言。\n归向灵岩岩底坐，道根圣果满祇园。",
        "dynasty": "宋",
        "collection_info": null
    },
    {
        "uuid": "1963c821c21d7b5f6c580ee3c55cb063",
        "title": "赠地理李生",
        "author": "马廷鸾",
        "content": "昆崙宇宙一株石，拄地撑天日夜浮。\n万古青山青未了，西风斜日黯凝眸。",
        "dynasty": "宋",
        "collection_info": null
    },
    {
        "uuid": "df626d281b3b4bd6c849d838b78d9a49",
        "title": "赠相者非常眼",
        "author": "马廷鸾",
        "content": "已分山林着此臞，一科端不补遗余。\n朝来忽遇非常眼，废却窗前半日书。",
        "dynasty": "宋",
        "collection_info": null
    },
    {
        "uuid": "b611c0160e5c24c04bc23ef160cf6cc3",
        "title": "赠相士二首  其一",
        "author": "马廷鸾",
        "content": "人物渺然吁可叹，凭谁指出植鳍翁。\n勤伊急向傅岩看，当在君王梦寐中。",
        "dynasty": "宋",
        "collection_info": null
    },
    {
        "uuid": "008d0933429a8020f8e6e3097fefc597",
        "title": "赠相士二首  其二",
        "author": "马廷鸾",
        "content": "处仲恰如王眼目，了翁旧识蔡精神。\n尽教识尽公卿相，不愿公卿属箇人。",
        "dynasty": "宋",
        "collection_info": null
    },
    {
        "uuid": "af4ff9c924d1e2174bd46b3f840811ac",
        "title": "酬县教徐志友",
        "author": "马廷鸾",
        "content": "二十五宗诗有派，九成宫帖字名家。\n何须奠去无人识，政自吟来与舅夸。",
        "dynasty": "宋",
        "collection_info": null
    },
    {
        "uuid": "830c6e29356306c70d0a1edd2dcfdc7a",
        "title": "奉谢龙山使君",
        "author": "马廷鸾",
        "content": "四美持来野老家，灯前儿女自讙譁。\n匙抄天上神仙饭，瓶插人间富贵花。\n剡雪尚堪书茧纸，吴霜聊欲寄乌纱。\n今朝新雨无人迹，莫向门前几箇夸。",
        "dynasty": "宋",
        "collection_info": null
    },
    {
        "uuid": "a0d12223548a86de168e658ec08e1d49",
        "title": "诗谢赵南冈",
        "author": "马廷鸾",
        "content": "早从诸暨厚相于，郭史能书也忆渠。\n万事只今同去鹤，十年依旧爱前鱼。\n试尝小缶烹莼玉，旋泼新醅漉酒酾。\n故旧不遗风韵在，犹存越绝几编书。",
        "dynasty": "宋",
        "collection_info": null
    },
    {
        "uuid": "f5ba864e18e4f88b65d1b599a52b4dac",
        "title": "谢龙山惠柱杖并求石铫四首  其一",
        "author": "马廷鸾",
        "content": "山窗闲笏倦支颐，出户犹嗟拟步迟。\n万事一条横楖栗，缘坡穿径走如驰。",
        "dynasty": "宋",
        "collection_info": null
    },
    {
        "uuid": "f86c2849a9603a4d6c87f07488ad2c24",
        "title": "谢龙山惠柱杖并求石铫四首  其二",
        "author": "马廷鸾",
        "content": "读书未把壮心降，瀹雪烹云听煮汤。\n浇我胸中过秦论，笑渠臧谷两忘羊。",
        "dynasty": "宋",
        "collection_info": null
    },
    {
        "uuid": "d6193959835cc4fd0322d04d64f96d14",
        "title": "谢龙山惠柱杖并求石铫四首  其三",
        "author": "马廷鸾",
        "content": "捷径新来竞朵颐，登山有道只逶迟。\n瘦藤独立西风上，看尽坡头万马驰。",
        "dynasty": "宋",
        "collection_info": null
    },
    {
        "uuid": "0eb4c526d121097a067492dfebe26116",
        "title": "谢龙山惠柱杖并求石铫四首  其四",
        "author": "马廷鸾",
        "content": "砖炉石铫竹方床，何必银瓶为泻汤。\n苦茗只堪浇菜肚，春风却负太官羊。",
        "dynasty": "宋",
        "collection_info": null
    },
    {
        "uuid": "33f69856c0f9bf15dcd610f8a6650658",
        "title": "题毛氏榴峰",
        "author": "马廷鸾",
        "content": "谁家马鬣怀先人，何人牛腰骋奇作。\n山高水长霜露濡，柏茂松深鸟乌落。\n曾玄有酒酹凄凉，翁仲无言卧冥寞。\n胥涛怒起越云横，血洒苍梧双泪落。",
        "dynasty": "宋",
        "collection_info": null
    },
    {
        "uuid": "72290c28443ee699cfc5153d7e77a142",
        "title": "创木行",
        "author": "马廷鸾",
        "content": "矫首昂霄上，刳心泣露余。\n高门封植旧，暴客斧斤初。\n斲作有瑕玉，创为无用樗。\n终当宿威凤，勿为汝欷歔。",
        "dynasty": "宋",
        "collection_info": null
    },
    {
        "uuid": "b2c91c6aa8a0b721735716b8349007c6",
        "title": "锦鸡",
        "author": "马廷鸾",
        "content": "照水栖山自一奇，绛冠雪羽岂人牺。\n明明在上今□望，是汝箪瓢捽茹时。",
        "dynasty": "宋",
        "collection_info": null
    },
    {
        "uuid": "57b627ac744d4d49c655d19f3b1c028a",
        "title": "余氏心晖堂",
        "author": "马廷鸾",
        "content": "客从银山来，遗我骊龙珠。\n高文伟大册，至宝耀室隅。\n一读心为眩，再读目为盱。\n夫记者为谁，颍封人之徒。\n人生天地间，母怀靡知愚。\n至恩嗟莫报，大节尤可吁。\n柏舟谅人只，蓼莪生子劬。\n所以茅季伟，鷄半馔设腴。\n所以王休证，鱼双甘旨需。\n此理有俱有，此心无息无。\n儿寒衣芦花，母在足欣娱。\n儿罪履中野，母怜自噫呜。\n高高心晖堂，申旦所依于。\n俨然其若存，何可离须臾。\n我吟方区区，我步方于于。\n起看物所性，因悟理不诬。\n怀哉反哺者，城头尾毕逋。",
        "dynasty": "宋",
        "collection_info": null
    },
    {
        "uuid": "136fabe7396542b6280c5d0aaa706ebf",
        "title": "方氏临清堂二首  其一",
        "author": "马廷鸾",
        "content": "割取风烟归此堂，尘缨更好濯沧浪。\n青山屋上下流水，永日翻书乐未央。",
        "dynasty": "宋",
        "collection_info": null
    },
    {
        "uuid": "64cf4628a5c00b2af5ddc4b3665d0bb8",
        "title": "方氏临清堂二首  其二",
        "author": "马廷鸾",
        "content": "陶翁归计已成迟，未折腰前好赋诗。\n到底尚称千载士，高人拈向此中题。",
        "dynasty": "宋",
        "collection_info": null
    },
    {
        "uuid": "cf88e3d6dd9ea1db658d32b05118cc47",
        "title": "徐氏拜荣堂",
        "author": "马廷鸾",
        "content": "银黉三组归去来，绣衣朱毂胡为哉。\n富贵熏天无足道，人间至乐归老莱。\n青衫随分当綵衣，阿母一笑生儿痴。\n笋生雪底冰下鱼，此事惟有天公知。\n吾母今年五十余，襟期正与君母俱。\n双瞳点漆髮未白，画堂茅舍各自如。\n何时两母俱徜徉，安舆来往陈壶觞。\n因观吾庐戏綵章，就赋君家拜荣堂。",
        "dynasty": "宋",
        "collection_info": null
    },
    {
        "uuid": "19f5309c3965fdea321ae0f10dfd5686",
        "title": "七月八夜宿东平精舍",
        "author": "马廷鸾",
        "content": "昨夜双星会鹊桥，好风佳月度今宵。\n天孙晓发银河落，帝昊秋成宝穑饶。\n玉露尚添荷缊藉，金风不惜柳飘飘。\n炉香直为攀髯苦，望断高空正泬寥。",
        "dynasty": "宋",
        "collection_info": null
    },
    {
        "uuid": "267e80ab3ffe0dab96d64176f55c34a7",
        "title": "宿斋和同僚韵",
        "author": "马廷鸾",
        "content": "羣玉峯头一望赊，枕书旧监忆乘槎。\n自从芸蠹三分席，何啻槐龙五见花。\n大典奏篇文综覈，清吟落笔字横斜。\n绝怜名辈诸公□，鞙璲如何趁佩霞。",
        "dynasty": "宋",
        "collection_info": null
    },
    {
        "uuid": "2ddf7e4c1931c327320895df696c252f",
        "title": "无题三首  其一",
        "author": "马廷鸾",
        "content": "大地生灵惜暵干，纸田不饱腐儒餐。\n闲将博士虀盐味，试上先生苜蓿盘。",
        "dynasty": "宋",
        "collection_info": null
    },
    {
        "uuid": "e06e8f962aeeacac608d1fc4e9e14946",
        "title": "无题三首  其二",
        "author": "马廷鸾",
        "content": "口语甘时心独异，中边甜处味方宜。\n诗情合荐东坡老，惭媿当年蜜荔枝。",
        "dynasty": "宋",
        "collection_info": null
    },
    {
        "uuid": "60d66cf901357ebdd45c85487c4032d6",
        "title": "无题三首  其三",
        "author": "马廷鸾",
        "content": "闻说江边起柁楼，欲将吾道付沧洲。\n三年恶瞰卢仝屋，一日轻装范蠡舟。\n蹈海高怀欣独往，济川好手蹇难留。\n樯阴舸下能容我，雨笠烟簑傲白鸥。",
        "dynasty": "宋",
        "collection_info": null
    },
    {
        "uuid": "22a03840b25912a87d32e7b2ea6e41ed",
        "title": "题林彦潜诗编",
        "author": "马廷鸾",
        "content": "快读诗人七鉅编，前身端合是逋仙。\n村翁溪老开吟社，媿我犹撑上水船。",
        "dynasty": "宋",
        "collection_info": null
    },
    {
        "uuid": "1edc86dc7c0cc553ba2c201431ba6259",
        "title": "读史有感",
        "author": "马廷鸾",
        "content": "永嘉直数到贞明，三百年间宇宙倾。\n草草梁陈貂尾续，纷纷云代犬牙争。\n谁知普六茹坚者，已向重光作噩生。\n毕竟开皇能混一，天公愦愦岂无情。",
        "dynasty": "宋",
        "collection_info": null
    },
    {
        "uuid": "4fee51d55eceb9e15004d427dfc0501e",
        "title": "送朱子式从军",
        "author": "马廷鸾",
        "content": "折镞奇勋在，衝冠怒气深。\n尧天日月大，禹甸曀霾侵。\n塞下将军令，隆中梁甫吟。\n酒行君可起，快展击胡心。",
        "dynasty": "宋",
        "collection_info": null
    },
    {
        "uuid": "45ca14abb334fb18b2141fc48255f44c",
        "title": "送文甫兄归番阳二首  其一",
        "author": "马廷鸾",
        "content": "白髮苍颜老弟兄，累年隔阔话情亲。\n杭京一访且千里，盘祖诸孙纔九人。\n扫榻少留深雨夜，着鞭又趁早霜晨。\n曾门有衍诗书泽，为计维垣蜜印新。",
        "dynasty": "宋",
        "collection_info": null
    },
    {
        "uuid": "c56fe1e5aba2b5e892be4b6ad9e395e8",
        "title": "送文甫兄归番阳二首  其二",
        "author": "马廷鸾",
        "content": "少小追随子佩青，如今相视鬓丝横。\n式相好矣天伦重，归去来兮世念轻。\n目送飞鸿云缥缈，身怜病鹤影伶仃。\n圣恩若许还农亩，依旧山窗共短檠。",
        "dynasty": "宋",
        "collection_info": null
    },
    {
        "uuid": "26fff47795be66056cf9e6bd36fc0891",
        "title": "本朝治衰高宗生",
        "author": "马廷鸾",
        "content": "岁逢渊献感炎精，创业中兴二主生。\n天启高皇符艺祖，人将大观拟天成。\n生民厌乱思平治，造物开先毓圣明。\n甲子□□□□亥，试从汉史漫推评。",
        "dynasty": "宋",
        "collection_info": null
    },
    {
        "uuid": "143d35e287b81fcfafa7863bfcc66106",
        "title": "梅岩",
        "author": "马廷鸾",
        "content": "卓哉青壁插晴空，古貌棱棱列士风。\n人物山川相与重，是间知有植鳍翁。",
        "dynasty": "宋",
        "collection_info": null
    },
    {
        "uuid": "289582c407dc554aab0147c3027e808f",
        "title": "披云堂歌",
        "author": "马廷鸾",
        "content": "痴云压陇如坚城，猛风击破如雄兵。\n寒溪古洞收不彻，有如奔车白旆归空营。\n林稍划划露微碧，玉匣渐见青铜精。\n影转西风流日脚，万斛黄金散空落。\n宝篦刮尽重瞳膜，倒盛一海春冰薄。\n世界倾在琉璃屏，神豪气爽肌骨清。\n便欲垂羽翰，飞上朝玉京。\n不须七椀秋江波，两腋自有清风生。\n长忆当年玉川子，慇懃会问苍生事。",
        "dynasty": "宋",
        "collection_info": null
    },
    {
        "uuid": "2097c1ccbba93f286450a9c32148efa6",
        "title": "老学楼",
        "author": "马廷鸾",
        "content": "元龙高卧仲宣忧，我独丛书置此楼。\n把卷欣将圣贤对，凭栏遮断古今愁。\n山前翠树森云表，林罅青秧匝壠头。\n收拾吟篇供老眼，陈登王粲总悠悠。",
        "dynasty": "宋",
        "collection_info": null
    },
    {
        "uuid": "137954aede2ad2f19354b50c416b8105",
        "title": "盘园",
        "author": "马廷鸾",
        "content": "云水乡中楼观开，溪山好处兴悠哉。\n平章风月归茶鼎，管领烟霞付酒杯。\n吟骨已成枯鹤瘦，机心莫遣狎鸥猜。\n大夫整顿干坤了，黄帽青鞋归去来。",
        "dynasty": "宋",
        "collection_info": null
    },
    {
        "uuid": "ce01868a626a2ab9f0075cbb412af7ac",
        "title": "四友相陪亭",
        "author": "马廷鸾",
        "content": "谁伴幽人饱岁寒，霜葩雪榦翠琅玕。\n眼前交道如渠少，好作长年耐久看。",
        "dynasty": "宋",
        "collection_info": null
    }
]